Workbook

Sheet Apr
A2: CB2025-2026.xlsx | C2: Anurag-Professional | D2: Status: | E2: Individual | G2: CASHBOOK | I2: PAN: | J2: AFIPG7802B | L2: Asst.Yr. | N2: Month | O2: =CHOOSE(MONTH(A6),"Jan","Feb","Mar","Apr","May","Jun","Jul","Aug","Sep","Oct","Nov","Dec") -> Apr
A4: Date | B4: Reciept A/c | C4: Reciept Particulars | D4: L.F. No. | E4: VNH | F4: Cash | G4: Cash | H4: Chq. | I4: Total | J4: Date | K4: Payment A/c | L4: Payment Particulars | M4: L.F. No. | N4: Cash | O4: Chq. | P4: Total | Q4: Balance
A6: 45383 | B6: Balance | C6: B/F | F6: 99619 | G6: =SUM(E6:F6) -> 99619 | I6: =I5+G6 -> 99619 | J6: 45383 | P6: =P5+N6 -> 0 | Q6: =I6-P6 -> 99619
A7: 45384 | G7: =SUM(E7:F7) -> 0 | I7: =I6+G7 -> 99619 | J7: 45384 | P7: =P6+N7 -> 0 | Q7: =I7-P7 -> 99619
A8: 45385 | G8: =SUM(E8:F8) -> 0 | I8: =I7+G8 -> 99619 | J8: 45385 | K8: Salary | L8: Neeraj | M8: 9 | N8: 3000 | P8: =P7+N8 -> 3000 | Q8: =I8-P8 -> 96619
A9: 45386 | G9: =SUM(E9:F9) -> 0 | I9: =I8+G9 -> 99619 | J9: 45386 | K9: Misc. | L9: Stationery | M9: 6 | N9: 280 | P9: =P8+N9 -> 3280 | Q9: =I9-P9 -> 96339
A10: 45387 | G10: =SUM(E10:F10) -> 0 | I10: =I9+G10 -> 99619 | J10: 45387 | P10: =P9+N10 -> 3280 | Q10: =I10-P10 -> 96339
A11: 45388 | G11: =SUM(E11:F11) -> 0 | I11: =I10+G11 -> 99619 | J11: 45388 | P11: =P10+N11 -> 3280 | Q11: =I11-P11 -> 96339
A12: 45389 | G12: =SUM(E12:F12) -> 0 | I12: =I11+G12 -> 99619 | J12: 45389 | P12: =P11+N12 -> 3280 | Q12: =I12-P12 -> 96339
A13: 45390 | G13: =SUM(E13:F13) -> 0 | I13: =I12+G13 -> 99619 | J13: 45390 | P13: =P12+N13 -> 3280 | Q13: =I13-P13 -> 96339
A14: 45391 | G14: =SUM(E14:F14) -> 0 | I14: =I13+G14 -> 99619 | J14: 45391 | K14: ICICI | L14: NFS/CASH WDL/410015026840/S1ACAG49/AGRA /09-04-241558 | N14: 10000 | P14: =P13+N14 -> 13280 | Q14: =I14-P14 -> 86339
A15: 45392 | B15: Patients | C15: UPI/410117325925/fee/akjain62@unionb/Union Bank of I/UOBD2EB54F43C8E4A92A1ACB3AFBF6ED855 | G15: =SUM(E15:F15) -> 0 | H15: 300 | I15: =I14+G15 -> 99619 | J15: 45392 | K15: ICICI | L15: UPI/410117325925/fee/akjain62@unionb/Union Bank of I/UOBD2EB54F43C8E4A92A1ACB3AFBF6ED855 | O15: 300 | P15: =P14+N15 -> 13280 | Q15: =I15-P15 -> 86339
A16: 45393 | G16: =SUM(E16:F16) -> 0 | I16: =I15+G16 -> 99619 | J16: 45393 | P16: =P15+N16 -> 13280 | Q16: =I16-P16 -> 86339
A17: 45394 | G17: =SUM(E17:F17) -> 0 | I17: =I16+G17 -> 99619 | J17: 45394 | P17: =P16+N17 -> 13280 | Q17: =I17-P17 -> 86339
A18: 45395 | G18: =SUM(E18:F18) -> 0 | I18: =I17+G18 -> 99619 | J18: 45395 | P18: =P17+N18 -> 13280 | Q18: =I18-P18 -> 86339
A19: 45396 | G19: =SUM(E19:F19) -> 0 | I19: =I18+G19 -> 99619 | J19: 45396 | P19: =P18+N19 -> 13280 | Q19: =I19-P19 -> 86339
A20: 45397 | G20: =SUM(E20:F20) -> 0 | I20: =I19+G20 -> 99619 | J20: 45397 | K20: Veh. Exp. | L20: Petrol | M20: 11 | N20: 500 | P20: =P19+N20 -> 13780 | Q20: =I20-P20 -> 85839
A21: 45398 | G21: =SUM(E21:F21) -> 0 | I21: =I20+G21 -> 99619 | J21: 45398 | P21: =P20+N21 -> 13780 | Q21: =I21-P21 -> 85839
A22: 45399 | G22: =SUM(E22:F22) -> 0 | I22: =I21+G22 -> 99619 | J22: 45399 | P22: =P21+N22 -> 13780 | Q22: =I22-P22 -> 85839
A23: 45400 | G23: =SUM(E23:F23) -> 0 | I23: =I22+G23 -> 99619 | J23: 45400 | P23: =P22+N23 -> 13780 | Q23: =I23-P23 -> 85839
A24: 45401 | G24: =SUM(E24:F24) -> 0 | I24: =I23+G24 -> 99619 | J24: 45401 | P24: =P23+N24 -> 13780 | Q24: =I24-P24 -> 85839
A25: 45402 | G25: =SUM(E25:F25) -> 0 | I25: =I24+G25 -> 99619 | J25: 45402 | P25: =P24+N25 -> 13780 | Q25: =I25-P25 -> 85839
A26: 45403 | G26: =SUM(E26:F26) -> 0 | I26: =I25+G26 -> 99619 | J26: 45403 | K26: Salary | L26: Gaurav | M26: 9 | N26: 3000 | P26: =P25+N26 -> 16780 | Q26: =I26-P26 -> 82839
A27: 45404 | D27: 8 | G27: =SUM(E27:F27) -> 0 | H27: 300 | I27: =I26+G27 -> 99619 | J27: 45404 | K27: ICICI | L27: UPI/311273166081/UPI/7409404440.wa.y/Kotak Mahindra /AXISWC3C4DB46691D4D54E08E7 | M27: 4 | O27: 300 | P27: =P26+N27 -> 16780 | Q27: =I27-P27 -> 82839
A28: 45405 | G28: =SUM(E28:F28) -> 0 | I28: =I27+G28 -> 99619 | J28: 45405 | P28: =P27+N28 -> 16780 | Q28: =I28-P28 -> 82839
A29: 45406 | G29: =SUM(E29:F29) -> 0 | I29: =I28+G29 -> 99619 | J29: 45406 | P29: =P28+N29 -> 16780 | Q29: =I29-P29 -> 82839
A30: 45407 | G30: =SUM(E30:F30) -> 0 | I30: =I29+G30 -> 99619 | J30: 45407 | P30: =P29+N30 -> 16780 | Q30: =I30-P30 -> 82839
A31: 45408 | G31: =SUM(E31:F31) -> 0 | I31: =I30+G31 -> 99619 | J31: 45408 | P31: =P30+N31 -> 16780 | Q31: =I31-P31 -> 82839
A32: 45409 | G32: =SUM(E32:F32) -> 0 | I32: =I31+G32 -> 99619 | J32: 45409 | P32: =P31+N32 -> 16780 | Q32: =I32-P32 -> 82839
A33: 45410 | G33: =SUM(E33:F33) -> 0 | I33: =I32+G33 -> 99619 | J33: 45410 | P33: =P32+N33 -> 16780 | Q33: =I33-P33 -> 82839
A34: 45411 | G34: =SUM(E34:F34) -> 0 | I34: =I33+G34 -> 99619 | J34: 45411 | P34: =P33+N34 -> 16780 | Q34: =I34-P34 -> 82839
A35: 45412 | G35: =SUM(E35:F35) -> 0 | I35: =I34+G35 -> 99619 | J35: 45412 | K35: Balance | L35: C/F | N35: =Q34 -> 82839 | P35: =P34+N35 -> 99619 | Q35: =I35-P35 -> 0
H37: =SUM(H6:H35) -> 600 | O37: =SUM(O6:O35) -> 600

Sheet May
A2: CB2025-2026.xlsx | C2: Anurag-Professional | D2: Status: | E2: Individual | G2: CASHBOOK | I2: PAN: | J2: AFIPG7802B | L2: Asst.Yr. | N2: Month | O2: =CHOOSE(MONTH(A6),"Jan","Feb","Mar","Apr","May","Jun","Jul","Aug","Sep","Oct","Nov","Dec") -> May
A4: Date | B4: Reciept A/c | C4: Reciept Particulars | D4: L.F. No. | E4: VNH | F4: Cash | G4: Cash | H4: Chq. | I4: Total | J4: Date | K4: Payment A/c | L4: Payment Particulars | M4: L.F. No. | N4: Cash | O4: Chq. | P4: Total | Q4: Balance
A6: 45413 | B6: Balance | C6: B/F | F6: =Apr!N35 -> 82839 | G6: =Apr!N35 -> 82839 | I6: =I5+G6 -> 82839 | J6: 45413 | P6: =P5+N6 -> 0 | Q6: =I6-P6 -> 82839
A7: 45414 | G7: =SUM(E7:F7) -> 0 | I7: =I6+G7 -> 82839 | J7: 45414 | P7: =P6+N7 -> 0 | Q7: =I7-P7 -> 82839
A8: 45415 | B8: ICICI | C8: NFS/S1ACAG49/CASH WDL/03-05-23 | D8: 4 | F8: 10000 | G8: =SUM(E8:F8) -> 10000 | I8: =I7+G8 -> 92839 | J8: 45415 | P8: =P7+N8 -> 0 | Q8: =I8-P8 -> 92839
A9: 45416 | G9: =SUM(E9:F9) -> 0 | I9: =I8+G9 -> 92839 | J9: 45416 | P9: =P8+N9 -> 0 | Q9: =I9-P9 -> 92839
A10: 45417 | G10: =SUM(E10:F10) -> 0 | I10: =I9+G10 -> 92839 | J10: 45417 | P10: =P9+N10 -> 0 | Q10: =I10-P10 -> 92839
A11: 45418 | G11: =SUM(E11:F11) -> 0 | I11: =I10+G11 -> 92839 | J11: 45418 | P11: =P10+N11 -> 0 | Q11: =I11-P11 -> 92839
A12: 45419 | G12: =SUM(E12:F12) -> 0 | I12: =I11+G12 -> 92839 | J12: 45419 | K12: Salary | L12: Neeraj | M12: 9 | N12: 3000 | P12: =P11+N12 -> 3000 | Q12: =I12-P12 -> 89839
A13: 45420 | G13: =SUM(E13:F13) -> 0 | I13: =I12+G13 -> 92839 | J13: 45420 | P13: =P12+N13 -> 3000 | Q13: =I13-P13 -> 89839
A14: 45421 | G14: =SUM(E14:F14) -> 0 | I14: =I13+G14 -> 92839 | J14: 45421 | P14: =P13+N14 -> 3000 | Q14: =I14-P14 -> 89839
A15: 45422 | G15: =SUM(E15:F15) -> 0 | I15: =I14+G15 -> 92839 | J15: 45422 | P15: =P14+N15 -> 3000 | Q15: =I15-P15 -> 89839
A16: 45423 | G16: =SUM(E16:F16) -> 0 | I16: =I15+G16 -> 92839 | J16: 45423 | P16: =P15+N16 -> 3000 | Q16: =I16-P16 -> 89839
A17: 45424 | G17: =SUM(E17:F17) -> 0 | I17: =I16+G17 -> 92839 | J17: 45424 | P17: =P16+N17 -> 3000 | Q17: =I17-P17 -> 89839
A18: 45425 | G18: =SUM(E18:F18) -> 0 | I18: =I17+G18 -> 92839 | J18: 45425 | P18: =P17+N18 -> 3000 | Q18: =I18-P18 -> 89839
A19: 45426 | G19: =SUM(E19:F19) -> 0 | I19: =I18+G19 -> 92839 | J19: 45426 | K19: Veh. Exp. | L19: Petrol | M19: 11 | N19: 500 | P19: =P18+N19 -> 3500 | Q19: =I19-P19 -> 89339
A20: 45427 | G20: =SUM(E20:F20) -> 0 | I20: =I19+G20 -> 92839 | J20: 45427 | P20: =P19+N20 -> 3500 | Q20: =I20-P20 -> 89339
A21: 45428 | G21: =SUM(E21:F21) -> 0 | I21: =I20+G21 -> 92839 | J21: 45428 | P21: =P20+N21 -> 3500 | Q21: =I21-P21 -> 89339
A22: 45429 | G22: =SUM(E22:F22) -> 0 | I22: =I21+G22 -> 92839 | J22: 45429 | P22: =P21+N22 -> 3500 | Q22: =I22-P22 -> 89339
A23: 45430 | G23: =SUM(E23:F23) -> 0 | I23: =I22+G23 -> 92839 | J23: 45430 | P23: =P22+N23 -> 3500 | Q23: =I23-P23 -> 89339
A24: 45431 | G24: =SUM(E24:F24) -> 0 | I24: =I23+G24 -> 92839 | J24: 45431 | P24: =P23+N24 -> 3500 | Q24: =I24-P24 -> 89339
A25: 45432 | G25: =SUM(E25:F25) -> 0 | I25: =I24+G25 -> 92839 | J25: 45432 | P25: =P24+N25 -> 3500 | Q25: =I25-P25 -> 89339
A26: 45433 | G26: =SUM(E26:F26) -> 0 | I26: =I25+G26 -> 92839 | J26: 45433 | P26: =P25+N26 -> 3500 | Q26: =I26-P26 -> 89339
A27: 45434 | B27: Patients | C27: TRF/MARUTINANDAN HEALTHCARE/004877/ICI/03.05.2024 | G27: =SUM(E27:F27) -> 0 | H27: =2160*1.1 -> 2376 | I27: =I26+G27 -> 92839 | J27: 45434 | K27: ICICI | L27: TRF/MARUTINANDAN HEALTHCARE/004877/ICI/03.05.2024 | M27: 9 | O27: 2160 | P27: =P26+N27 -> 3500 | Q27: =I27-P27 -> 89339
A28: 45434 | B28: Patients | C28: TRF/SHRI MARUTINANDAN/004852/ICI/30.04.2024 | I28: =I27+G28 -> 92839 | K28: TDStoIT | O28: 216 | P28: =P27+N28 -> 3500 | Q28: =I28-P28 -> 89339
A29: 45434 | H29: =4950*1.1 -> 5445 | I29: =I28+G29 -> 92839 | K29: ICICI | L29: TRF/SHRI MARUTINANDAN/004852/ICI/30.04.2024 | O29: 4950 | P29: =P28+N29 -> 3500 | Q29: =I29-P29 -> 89339
A30: 45434 | G30: =SUM(E30:F30) -> 0 | I30: =I29+G30 -> 92839 | J30: 45434 | K30: TDStoIT | O30: 495 | P30: =P29+N30 -> 3500 | Q30: =I30-P30 -> 89339
A31: 45436 | G31: =SUM(E31:F31) -> 0 | I31: =I30+G31 -> 92839 | J31: 45436 | P31: =P30+N31 -> 3500 | Q31: =I31-P31 -> 89339
A32: 45437 | G32: =SUM(E32:F32) -> 0 | I32: =I31+G32 -> 92839 | J32: 45437 | P32: =P31+N32 -> 3500 | Q32: =I32-P32 -> 89339
A33: 45438 | G33: =SUM(E33:F33) -> 0 | I33: =I32+G33 -> 92839 | J33: 45438 | P33: =P32+N33 -> 3500 | Q33: =I33-P33 -> 89339
A34: 45439 | G34: =SUM(E34:F34) -> 0 | I34: =I33+G34 -> 92839 | J34: 45439 | P34: =P33+N34 -> 3500 | Q34: =I34-P34 -> 89339
A35: 45440 | G35: =SUM(E35:F35) -> 0 | I35: =I34+G35 -> 92839 | J35: 45440 | P35: =P34+N35 -> 3500 | Q35: =I35-P35 -> 89339
A36: 45441 | B36: ICICI | C36: NFS/S1ACAG49/CASH WDL/28-05-23 | D36: 4 | F36: 10000 | G36: =SUM(E36:F36) -> 10000 | I36: =I35+G36 -> 102839 | J36: 45441 | P36: =P35+N36 -> 3500 | Q36: =I36-P36 -> 99339
A37: 45442 | G37: =SUM(E37:F37) -> 0 | I37: =I36+G37 -> 102839 | J37: 45442 | K37: Veh. Exp. | L37: Petrol | M37: 11 | N37: 2000 | P37: =P36+N37 -> 5500 | Q37: =I37-P37 -> 97339
A38: 45443 | G38: =SUM(E38:F38) -> 0 | I38: =I37+G38 -> 102839 | J38: 45443 | P38: =P37+N38 -> 5500 | Q38: =I38-P38 -> 97339
A39: 45444 | G39: =SUM(E39:F39) -> 0 | I39: =I38+G39 -> 102839 | J39: 45444 | K39: Balance | L39: C/F | N39: =Q38 -> 97339 | P39: =P38+N39 -> 102839 | Q39: =I39-P39 -> 0
H41: =SUM(H6:H39) -> 7821 | O41: =SUM(O6:O39) -> 7821

Sheet Jun
A2: CB2025-2026.xlsx | C2: Anurag-Professional | D2: Status: | E2: Individual | G2: CASHBOOK | I2: PAN: | J2: AFIPG7802B | L2: Asst.Yr. | N2: Month | O2: =CHOOSE(MONTH(A6),"Jan","Feb","Mar","Apr","May","Jun","Jul","Aug","Sep","Oct","Nov","Dec") -> Jun
A4: Date | B4: Reciept A/c | C4: Reciept Particulars | D4: L.F. No. | E4: VNH | F4: Cash | G4: Cash | H4: Chq. | I4: Total | J4: Date | K4: Payment A/c | L4: Payment Particulars | M4: L.F. No. | N4: Cash | O4: Chq. | P4: Total | Q4: Balance
A6: 45444 | B6: Balance | C6: B/F | F6: =May!N39 -> 97339 | G6: =May!N39 -> 97339 | I6: =I5+G6 -> 97339 | J6: 45444 | P6: =P5+N6 -> 0 | Q6: =I6-P6 -> 97339
A7: 45444 | B7: Patients | C7: CLG/SHRI MARUTI NANDAN/277853/CAB/22.05.2024 | D7: 1 | G7: =SUM(E7:F7) -> 0 | I7: =I6+G7 -> 97339 | J7: 45444 | K7: ICICI | L7: CLG/SHRI MARUTI NANDAN/277853/CAB/22.05.2024 | O7: 6300 | P7: =P6+N7 -> 0 | Q7: =I7-P7 -> 97339
A8: 45444 | G8: =SUM(E8:F8) -> 0 | I8: =I7+G8 -> 97339 | J8: 45444 | K8: TDStoIT | O8: 630 | P8: =P7+N8 -> 0 | Q8: =I8-P8 -> 97339
A9: 45447 | G9: =SUM(E9:F9) -> 0 | I9: =I8+G9 -> 97339 | J9: 45447 | P9: =P8+N9 -> 0 | Q9: =I9-P9 -> 97339
A10: 45448 | G10: =SUM(E10:F10) -> 0 | I10: =I9+G10 -> 97339 | J10: 45448 | P10: =P9+N10 -> 0 | Q10: =I10-P10 -> 97339
A11: 45449 | G11: =SUM(E11:F11) -> 0 | I11: =I10+G11 -> 97339 | J11: 45449 | P11: =P10+N11 -> 0 | Q11: =I11-P11 -> 97339
A12: 45450 | G12: =SUM(E12:F12) -> 0 | I12: =I11+G12 -> 97339 | J12: 45450 | P12: =P11+N12 -> 0 | Q12: =I12-P12 -> 97339
A13: 45451 | G13: =SUM(E13:F13) -> 0 | I13: =I12+G13 -> 97339 | J13: 45451 | P13: =P12+N13 -> 0 | Q13: =I13-P13 -> 97339
A14: 45452 | G14: =SUM(E14:F14) -> 0 | I14: =I13+G14 -> 97339 | J14: 45452 | P14: =P13+N14 -> 0 | Q14: =I14-P14 -> 97339
A15: 45453 | G15: =SUM(E15:F15) -> 0 | I15: =I14+G15 -> 97339 | J15: 45453 | P15: =P14+N15 -> 0 | Q15: =I15-P15 -> 97339
A16: 45454 | G16: =SUM(E16:F16) -> 0 | I16: =I15+G16 -> 97339 | J16: 45454 | P16: =P15+N16 -> 0 | Q16: =I16-P16 -> 97339
A17: 45455 | G17: =SUM(E17:F17) -> 0 | I17: =I16+G17 -> 97339 | J17: 45455 | P17: =P16+N17 -> 0 | Q17: =I17-P17 -> 97339
A18: 45456 | G18: =SUM(E18:F18) -> 0 | I18: =I17+G18 -> 97339 | J18: 45456 | P18: =P17+N18 -> 0 | Q18: =I18-P18 -> 97339
A19: 45457 | G19: =SUM(E19:F19) -> 0 | I19: =I18+G19 -> 97339 | J19: 45457 | P19: =P18+N19 -> 0 | Q19: =I19-P19 -> 97339
A20: 45458 | G20: =SUM(E20:F20) -> 0 | I20: =I19+G20 -> 97339 | J20: 45458 | P20: =P19+N20 -> 0 | Q20: =I20-P20 -> 97339
A21: 45459 | G21: =SUM(E21:F21) -> 0 | I21: =I20+G21 -> 97339 | J21: 45459 | P21: =P20+N21 -> 0 | Q21: =I21-P21 -> 97339
A22: 45460 | G22: =SUM(E22:F22) -> 0 | I22: =I21+G22 -> 97339 | J22: 45460 | K22: Veh. Exp. | L22: Petrol | M22: 11 | N22: 500 | P22: =P21+N22 -> 500 | Q22: =I22-P22 -> 96839
A23: 45461 | G23: =SUM(E23:F23) -> 0 | I23: =I22+G23 -> 97339 | J23: 45461 | P23: =P22+N23 -> 500 | Q23: =I23-P23 -> 96839
A24: 45462 | G24: =SUM(E24:F24) -> 0 | I24: =I23+G24 -> 97339 | J24: 45462 | P24: =P23+N24 -> 500 | Q24: =I24-P24 -> 96839
A25: 45463 | G25: =SUM(E25:F25) -> 0 | I25: =I24+G25 -> 97339 | J25: 45463 | P25: =P24+N25 -> 500 | Q25: =I25-P25 -> 96839
A26: 45464 | G26: =SUM(E26:F26) -> 0 | I26: =I25+G26 -> 97339 | J26: 45464 | P26: =P25+N26 -> 500 | Q26: =I26-P26 -> 96839
A27: 45465 | G27: =SUM(E27:F27) -> 0 | I27: =I26+G27 -> 97339 | J27: 45465 | K27: Salary | L27: Gaurav | M27: 9 | N27: 3000 | P27: =P26+N27 -> 3500 | Q27: =I27-P27 -> 93839
A28: 45466 | G28: =SUM(E28:F28) -> 0 | I28: =I27+G28 -> 97339 | J28: 45466 | P28: =P27+N28 -> 3500 | Q28: =I28-P28 -> 93839
A29: 45467 | G29: =SUM(E29:F29) -> 0 | I29: =I28+G29 -> 97339 | J29: 45467 | P29: =P28+N29 -> 3500 | Q29: =I29-P29 -> 93839
A30: 45468 | G30: =SUM(E30:F30) -> 0 | I30: =I29+G30 -> 97339 | J30: 45468 | P30: =P29+N30 -> 3500 | Q30: =I30-P30 -> 93839
A31: 45469 | G31: =SUM(E31:F31) -> 0 | I31: =I30+G31 -> 97339 | J31: 45469 | P31: =P30+N31 -> 3500 | Q31: =I31-P31 -> 93839
A32: 45470 | G32: =SUM(E32:F32) -> 0 | I32: =I31+G32 -> 97339 | J32: 45470 | P32: =P31+N32 -> 3500 | Q32: =I32-P32 -> 93839
A33: 45471 | B33: ICICI | C33: NFS/S1ACAG49/CASH WDL/28-06-23 | D33: 4 | F33: 10000 | G33: =SUM(E33:F33) -> 10000 | I33: =I32+G33 -> 107339 | J33: 45471 | P33: =P32+N33 -> 3500 | Q33: =I33-P33 -> 103839
A34: 45472 | G34: =SUM(E34:F34) -> 0 | I34: =I33+G34 -> 107339 | J34: 45472 | P34: =P33+N34 -> 3500 | Q34: =I34-P34 -> 103839
A35: 45473 | G35: =SUM(E35:F35) -> 0 | I35: =I34+G35 -> 107339 | J35: 45473 | K35: Balance | L35: C/F | N35: =Q34 -> 103839 | P35: =P34+N35 -> 107339 | Q35: =I35-P35 -> 0
H37: =SUM(H6:H36) -> 0 | O37: =SUM(O6:O36) -> 6930

Sheet Jul
A2: CB2025-2026.xlsx | C2: Anurag-Professional | D2: Status: | E2: Individual | G2: CASHBOOK | I2: PAN: | J2: AFIPG7802B | L2: Asst.Yr. | N2: Month | O2: =CHOOSE(MONTH(A6),"Jan","Feb","Mar","Apr","May","Jun","Jul","Aug","Sep","Oct","Nov","Dec") -> Jul
A4: Date | B4: Reciept A/c | C4: Reciept Particulars | D4: L.F. No. | E4: VNH | F4: Cash | G4: Cash | H4: Chq. | I4: Total | J4: Date | K4: Payment A/c | L4: Payment Particulars | M4: L.F. No. | N4: Cash | O4: Chq. | P4: Total | Q4: Balance
A6: 45474 | B6: Balance | C6: B/F | F6: =Jun!N35 -> 103839 | G6: =Jun!N35 -> 103839 | I6: =I5+G6 -> 103839 | J6: 45474 | P6: =P5+N6 -> 0 | Q6: =I6-P6 -> 103839
A7: 45475 | G7: =SUM(E7:F7) -> 0 | I7: =I6+G7 -> 103839 | J7: 45475 | P7: =P6+N7 -> 0 | Q7: =I7-P7 -> 103839
A8: 45476 | G8: =SUM(E8:F8) -> 0 | I8: =I7+G8 -> 103839 | J8: 45476 | P8: =P7+N8 -> 0 | Q8: =I8-P8 -> 103839
A9: 45477 | G9: =SUM(E9:F9) -> 0 | I9: =I8+G9 -> 103839 | J9: 45477 | K9: Salary | L9: Neeraj | M9: 9 | N9: 3000 | P9: =P8+N9 -> 3000 | Q9: =I9-P9 -> 100839
A10: 45478 | B10: Patients | C10: TRF/SHRI MARUTI NANDAN/004980/ICI/22.06.2024 | G10: =SUM(E10:F10) -> 0 | H10: =2340*1.1 -> 2574 | I10: =I9+G10 -> 103839 | J10: 45478 | K10: ICICI | L10: TRF/SHRI MARUTI NANDAN/004980/ICI/22.06.2024 | O10: 2340 | P10: =P9+N10 -> 3000 | Q10: =I10-P10 -> 100839
A11: 45478 | G11: =SUM(E11:F11) -> 0 | I11: =I10+G11 -> 103839 | J11: 45478 | K11: TDStoIT | O11: 234 | P11: =P10+N11 -> 3000 | Q11: =I11-P11 -> 100839
A12: 45478 | B12: Patients | C12: TRF/SHRI MARUTINANDAN HEALTH/004964/ICI/21.06.2024 | G12: =SUM(E12:F12) -> 0 | H12: =2430*1.1 -> 2673 | I12: =I11+G12 -> 103839 | J12: 45478 | K12: ICICI | L12: TRF/SHRI MARUTINANDAN HEALTH/004964/ICI/21.06.2024 | O12: 2430 | P12: =P11+N12 -> 3000 | Q12: =I12-P12 -> 100839
A13: 45478 | G13: =SUM(E13:F13) -> 0 | I13: =I12+G13 -> 103839 | J13: 45478 | K13: TDStoIT | O13: 243 | P13: =P12+N13 -> 3000 | Q13: =I13-P13 -> 100839
A14: 45482 | G14: =SUM(E14:F14) -> 0 | I14: =I13+G14 -> 103839 | J14: 45482 | P14: =P13+N14 -> 3000 | Q14: =I14-P14 -> 100839
A15: 45483 | G15: =SUM(E15:F15) -> 0 | I15: =I14+G15 -> 103839 | J15: 45483 | P15: =P14+N15 -> 3000 | Q15: =I15-P15 -> 100839
A16: 45484 | G16: =SUM(E16:F16) -> 0 | I16: =I15+G16 -> 103839 | J16: 45484 | K16: Veh. Exp. | L16: Petrol | M16: 11 | N16: 500 | P16: =P15+N16 -> 3500 | Q16: =I16-P16 -> 100339
A17: 45485 | G17: =SUM(E17:F17) -> 0 | I17: =I16+G17 -> 103839 | J17: 45485 | P17: =P16+N17 -> 3500 | Q17: =I17-P17 -> 100339
A18: 45486 | G18: =SUM(E18:F18) -> 0 | I18: =I17+G18 -> 103839 | J18: 45486 | P18: =P17+N18 -> 3500 | Q18: =I18-P18 -> 100339
A19: 45487 | G19: =SUM(E19:F19) -> 0 | I19: =I18+G19 -> 103839 | J19: 45487 | P19: =P18+N19 -> 3500 | Q19: =I19-P19 -> 100339
A20: 45488 | G20: =SUM(E20:F20) -> 0 | I20: =I19+G20 -> 103839 | J20: 45488 | P20: =P19+N20 -> 3500 | Q20: =I20-P20 -> 100339
A21: 45489 | G21: =SUM(E21:F21) -> 0 | I21: =I20+G21 -> 103839 | J21: 45489 | P21: =P20+N21 -> 3500 | Q21: =I21-P21 -> 100339
A22: 45490 | G22: =SUM(E22:F22) -> 0 | I22: =I21+G22 -> 103839 | J22: 45490 | P22: =P21+N22 -> 3500 | Q22: =I22-P22 -> 100339
A23: 45491 | G23: =SUM(E23:F23) -> 0 | I23: =I22+G23 -> 103839 | J23: 45491 | P23: =P22+N23 -> 3500 | Q23: =I23-P23 -> 100339
A24: 45492 | G24: =SUM(E24:F24) -> 0 | I24: =I23+G24 -> 103839 | J24: 45492 | P24: =P23+N24 -> 3500 | Q24: =I24-P24 -> 100339
A25: 45493 | G25: =SUM(E25:F25) -> 0 | I25: =I24+G25 -> 103839 | J25: 45493 | P25: =P24+N25 -> 3500 | Q25: =I25-P25 -> 100339
A26: 45494 | G26: =SUM(E26:F26) -> 0 | I26: =I25+G26 -> 103839 | J26: 45494 | P26: =P25+N26 -> 3500 | Q26: =I26-P26 -> 100339
A27: 45495 | G27: =SUM(E27:F27) -> 0 | I27: =I26+G27 -> 103839 | J27: 45495 | P27: =P26+N27 -> 3500 | Q27: =I27-P27 -> 100339
A28: 45496 | G28: =SUM(E28:F28) -> 0 | I28: =I27+G28 -> 103839 | J28: 45496 | K28: Salary | L28: Gaurav | M28: 9 | N28: 3000 | P28: =P27+N28 -> 6500 | Q28: =I28-P28 -> 97339
A29: 45497 | B29: Patients | C29: CLG/SHRI MARUTI/278050/CAB/18.07.2024 | G29: =SUM(E29:F29) -> 0 | H29: =2430*1.1 -> 2673 | I29: =I28+G29 -> 103839 | J29: 45497 | K29: ICICI | L29: CLG/SHRI MARUTI/278050/CAB/18.07.2024 | M29: 4 | O29: 2430 | P29: =P28+N29 -> 6500 | Q29: =I29-P29 -> 97339
A30: 45497 | G30: =SUM(E30:F30) -> 0 | I30: =I29+G30 -> 103839 | J30: 45497 | K30: TDStoIT | M30: 10 | O30: 243 | P30: =P29+N30 -> 6500 | Q30: =I30-P30 -> 97339
A31: 45497 | B31: Patients | C31: CLG/SHRI MARUTI/278048/CAB/18.07.2024 | G31: =SUM(E31:F31) -> 0 | H31: =3780*1.1 -> 4158 | I31: =I30+G31 -> 103839 | J31: 45497 | K31: ICICI | L31: CLG/SHRI MARUTI/278048/CAB/18.07.2024 | M31: 4 | O31: 3780 | P31: =P30+N31 -> 6500 | Q31: =I31-P31 -> 97339
A32: 45497 | G32: =SUM(E32:F32) -> 0 | I32: =I31+G32 -> 103839 | J32: 45497 | K32: TDStoIT | M32: 10 | O32: 378 | P32: =P31+N32 -> 6500 | Q32: =I32-P32 -> 97339
A33: 45501 | G33: =SUM(E33:F33) -> 0 | I33: =I32+G33 -> 103839 | J33: 45501 | P33: =P32+N33 -> 6500 | Q33: =I33-P33 -> 97339
A34: 45502 | G34: =SUM(E34:F34) -> 0 | I34: =I33+G34 -> 103839 | J34: 45502 | K34: Veh. Exp. | L34: Petrol | M34: 11 | N34: 500 | P34: =P33+N34 -> 7000 | Q34: =I34-P34 -> 96839
A35: 45503 | B35: ICICI | C35: ATM/S1CNQ071/CASH WDL/29-07-23 | D35: 4 | F35: 10000 | G35: =SUM(E35:F35) -> 10000 | I35: =I34+G35 -> 113839 | J35: 45503 | P35: =P34+N35 -> 7000 | Q35: =I35-P35 -> 106839
A36: 45504 | G36: =SUM(E36:F36) -> 0 | I36: =I35+G36 -> 113839 | J36: 45504 | P36: =P35+N36 -> 7000 | Q36: =I36-P36 -> 106839
A37: 45504 | G37: =SUM(E37:F37) -> 0 | I37: =I36+G37 -> 113839 | J37: 45504 | K37: Balance | L37: C/F | N37: =Q36 -> 106839 | P37: =P36+N37 -> 113839 | Q37: =I37-P37 -> 0
H39: =SUM(H6:H37) -> 12078 | O39: =SUM(O6:O37) -> 12078

Sheet Aug
A2: CB2025-2026.xlsx | C2: Anurag-Professional | D2: Status: | E2: Individual | G2: CASHBOOK | I2: PAN: | J2: AFIPG7802B | L2: Asst.Yr. | N2: Month | O2: =CHOOSE(MONTH(A6),"Jan","Feb","Mar","Apr","May","Jun","Jul","Aug","Sep","Oct","Nov","Dec") -> Aug
A4: Date | B4: Reciept A/c | C4: Reciept Particulars | D4: L.F. No. | E4: VNH | F4: Cash | G4: Cash | H4: Chq. | I4: Total | J4: Date | K4: Payment A/c | L4: Payment Particulars | M4: L.F. No. | N4: Cash | O4: Chq. | P4: Total | Q4: Balance
A6: 45505 | B6: Balance | C6: B/F | F6: =Jul!N37 -> 106839 | G6: =Jul!N37 -> 106839 | I6: =I5+G6 -> 106839 | J6: 45505 | P6: =P5+N6 -> 0 | Q6: =I6-P6 -> 106839
A7: 45506 | G7: =SUM(E7:F7) -> 0 | I7: =I6+G7 -> 106839 | J7: 45506 | K7: Salary | L7: Neeraj | M7: 9 | N7: 3000 | P7: =P6+N7 -> 3000 | Q7: =I7-P7 -> 103839
A8: 45507 | G8: =SUM(E8:F8) -> 0 | I8: =I7+G8 -> 106839 | J8: 45507 | P8: =P7+N8 -> 3000 | Q8: =I8-P8 -> 103839
A9: 45508 | G9: =SUM(E9:F9) -> 0 | I9: =I8+G9 -> 106839 | J9: 45508 | P9: =P8+N9 -> 3000 | Q9: =I9-P9 -> 103839
A10: 45509 | G10: =SUM(E10:F10) -> 0 | I10: =I9+G10 -> 106839 | J10: 45509 | P10: =P9+N10 -> 3000 | Q10: =I10-P10 -> 103839
A11: 45510 | G11: =SUM(E11:F11) -> 0 | I11: =I10+G11 -> 106839 | J11: 45510 | P11: =P10+N11 -> 3000 | Q11: =I11-P11 -> 103839
A12: 45511 | G12: =SUM(E12:F12) -> 0 | I12: =I11+G12 -> 106839 | J12: 45511 | P12: =P11+N12 -> 3000 | Q12: =I12-P12 -> 103839
A13: 45512 | G13: =SUM(E13:F13) -> 0 | I13: =I12+G13 -> 106839 | J13: 45512 | P13: =P12+N13 -> 3000 | Q13: =I13-P13 -> 103839
A14: 45513 | G14: =SUM(E14:F14) -> 0 | I14: =I13+G14 -> 106839 | J14: 45513 | P14: =P13+N14 -> 3000 | Q14: =I14-P14 -> 103839
A15: 45514 | G15: =SUM(E15:F15) -> 0 | I15: =I14+G15 -> 106839 | J15: 45514 | P15: =P14+N15 -> 3000 | Q15: =I15-P15 -> 103839
A16: 45515 | G16: =SUM(E16:F16) -> 0 | I16: =I15+G16 -> 106839 | J16: 45515 | P16: =P15+N16 -> 3000 | Q16: =I16-P16 -> 103839
A17: 45516 | G17: =SUM(E17:F17) -> 0 | I17: =I16+G17 -> 106839 | J17: 45516 | P17: =P16+N17 -> 3000 | Q17: =I17-P17 -> 103839
A18: 45517 | G18: =SUM(E18:F18) -> 0 | I18: =I17+G18 -> 106839 | J18: 45517 | P18: =P17+N18 -> 3000 | Q18: =I18-P18 -> 103839
A19: 45518 | G19: =SUM(E19:F19) -> 0 | I19: =I18+G19 -> 106839 | J19: 45518 | P19: =P18+N19 -> 3000 | Q19: =I19-P19 -> 103839
... A26: 45525 | G26: =SUM(E26:F26) -> 0 | I26: =I25+G26 -> 106839 | J26: 45525 | P26: =P25+N26 -> 3000 | Q26: =I26-P26 -> 103839
A27: 45526 | B27: Patients | C27: TRF/SHRI MARUTINANDAN HEALTH/005057/ICI/27.07.2024 | D27: 8 | G27: =SUM(E27:F27) -> 0 | H27: =18180*1.1 -> 19998 | I27: =I26+G27 -> 106839 | J27: 45526 | K27: ICICI | L27: TRF/SHRI MARUTINANDAN HEALTH/005057/ICI/27.07.2024 | M27: 4 | O27: 18180 | P27: =P26+N27 -> 3000 | Q27: =I27-P27 -> 103839
A28: 45526 | G28: =SUM(E28:F28) -> 0 | I28: =I27+G28 -> 106839 | J28: 45526 | K28: TDStoIT | M28: 10 | O28: 1818 | P28: =P27+N28 -> 3000 | Q28: =I28-P28 -> 103839
A29: 45527 | B29: Patients | C29: CLG/SHRI MARUTI NANDAN/278144/CAB/08.08.2024 | D29: 8 | G29: =SUM(E29:F29) -> 0 | H29: =11160*1.1 -> 12276 | I29: =I28+G29 -> 106839 | J29: 45527 | K29: ICICI | L29: CLG/SHRI MARUTI NANDAN/278144/CAB/08.08.2024 | M29: 4 | O29: 11160 | P29: =P28+N29 -> 3000 | Q29: =I29-P29 -> 103839
A30: 45527 | G30: =SUM(E30:F30) -> 0 | I30: =I29+G30 -> 106839 | J30: 45527 | K30: TDStoIT | M30: 10 | O30: 1116 | P30: =P29+N30 -> 3000 | Q30: =I30-P30 -> 103839
A31: 45530 | G31: =SUM(E31:F31) -> 0 | I31: =I30+G31 -> 106839 | J31: 45530 | P31: =P30+N31 -> 3000 | Q31: =I31-P31 -> 103839
A32: 45531 | G32: =SUM(E32:F32) -> 0 | I32: =I31+G32 -> 106839 | J32: 45531 | K32: Veh. Exp. | L32: Petrol | M32: 11 | N32: 500 | P32: =P31+N32 -> 3500 | Q32: =I32-P32 -> 103339
A33: 45532 | G33: =SUM(E33:F33) -> 0 | I33: =I32+G33 -> 106839 | J33: 45532 | P33: =P32+N33 -> 3500 | Q33: =I33-P33 -> 103339
A34: 45533 | B34: ICICI | C34: NFS/ID131801/CASH WDL/28-08-23 | D34: 4 | F34: 10000 | G34: =SUM(E34:F34) -> 10000 | I34: =I33+G34 -> 116839 | J34: 45533 | P34: =P33+N34 -> 3500 | Q34: =I34-P34 -> 113339
A35: 45534 | G35: =SUM(E35:F35) -> 0 | I35: =I34+G35 -> 116839 | J35: 45534 | P35: =P34+N35 -> 3500 | Q35: =I35-P35 -> 113339
A36: 45535 | G36: =SUM(E36:F36) -> 0 | I36: =I35+G36 -> 116839 | J36: 45535 | P36: =P35+N36 -> 3500 | Q36: =I36-P36 -> 113339
A37: 45535 | G37: =SUM(E37:F37) -> 0 | I37: =I36+G37 -> 116839 | J37: 45535 | K37: Balance | L37: C/F | N37: =Q36 -> 113339 | P37: =P36+N37 -> 116839 | Q37: =I37-P37 -> 0
H39: =SUM(H6:H37) -> 32274 | O39: =SUM(O6:O37) -> 32274

Sheet Sep
A2: CB2025-2026.xlsx | C2: Anurag-Professional | D2: Status: | E2: Individual | G2: CASHBOOK | I2: PAN: | J2: AFIPG7802B | L2: Asst.Yr. | N2: Month | O2: =CHOOSE(MONTH(A6),"Jan","Feb","Mar","Apr","May","Jun","Jul","Aug","Sep","Oct","Nov","Dec") -> Sep
A4: Date | B4: Reciept A/c | C4: Reciept Particulars | D4: L.F. No. | E4: VNH | F4: Cash | G4: Cash | H4: Chq. | I4: Total | J4: Date | K4: Payment A/c | L4: Payment Particulars | M4: L.F. No. | N4: Cash | O4: Chq. | P4: Total | Q4: Balance
A6: 45536 | B6: Balance | C6: B/F | F6: =Aug!N37 -> 113339 | G6: =Aug!N37 -> 113339 | I6: =I5+G6 -> 113339 | J6: 45536 | P6: =P5+N6 -> 0 | Q6: =I6-P6 -> 113339
A7: 45537 | G7: =SUM(E7:F7) -> 0 | I7: =I6+G7 -> 113339 | J7: 45537 | K7: Salary | L7: Neeraj | M7: 9 | N7: 3000 | P7: =P6+N7 -> 3000 | Q7: =I7-P7 -> 110339
A8: 45538 | G8: =SUM(E8:F8) -> 0 | I8: =I7+G8 -> 113339 | J8: 45538 | P8: =P7+N8 -> 3000 | Q8: =I8-P8 -> 110339
A9: 45539 | G9: =SUM(E9:F9) -> 0 | I9: =I8+G9 -> 113339 | J9: 45539 | P9: =P8+N9 -> 3000 | Q9: =I9-P9 -> 110339
A10: 45540 | G10: =SUM(E10:F10) -> 0 | I10: =I9+G10 -> 113339 | J10: 45540 | P10: =P9+N10 -> 3000 | Q10: =I10-P10 -> 110339
A11: 45541 | G11: =SUM(E11:F11) -> 0 | I11: =I10+G11 -> 113339 | J11: 45541 | P11: =P10+N11 -> 3000 | Q11: =I11-P11 -> 110339
A12: 45542 | G12: =SUM(E12:F12) -> 0 | I12: =I11+G12 -> 113339 | J12: 45542 | P12: =P11+N12 -> 3000 | Q12: =I12-P12 -> 110339
A13: 45543 | G13: =SUM(E13:F13) -> 0 | I13: =I12+G13 -> 113339 | J13: 45543 | P13: =P12+N13 -> 3000 | Q13: =I13-P13 -> 110339
A14: 45544 | G14: =SUM(E14:F14) -> 0 | I14: =I13+G14 -> 113339 | J14: 45544 | P14: =P13+N14 -> 3000 | Q14: =I14-P14 -> 110339
A15: 45545 | G15: =SUM(E15:F15) -> 0 | I15: =I14+G15 -> 113339 | J15: 45545 | P15: =P14+N15 -> 3000 | Q15: =I15-P15 -> 110339
A16: 45546 | G16: =SUM(E16:F16) -> 0 | I16: =I15+G16 -> 113339 | J16: 45546 | P16: =P15+N16 -> 3000 | Q16: =I16-P16 -> 110339
A17: 45547 | G17: =SUM(E17:F17) -> 0 | I17: =I16+G17 -> 113339 | J17: 45547 | P17: =P16+N17 -> 3000 | Q17: =I17-P17 -> 110339
A18: 45548 | G18: =SUM(E18:F18) -> 0 | I18: =I17+G18 -> 113339 | J18: 45548 | K18: Veh. Exp. | L18: Petrol | M18: 11 | N18: 2000 | P18: =P17+N18 -> 5000 | Q18: =I18-P18 -> 108339
A19: 45549 | G19: =SUM(E19:F19) -> 0 | I19: =I18+G19 -> 113339 | J19: 45549 | P19: =P18+N19 -> 5000 | Q19: =I19-P19 -> 108339
A20: 45550 | G20: =SUM(E20:F20) -> 0 | I20: =I19+G20 -> 113339 | J20: 45550 | P20: =P19+N20 -> 5000 | Q20: =I20-P20 -> 108339
A21: 45551 | G21: =SUM(E21:F21) -> 0 | I21: =I20+G21 -> 113339 | J21: 45551 | P21: =P20+N21 -> 5000 | Q21: =I21-P21 -> 108339
A22: 45552 | B22: ICICI | C22: NFS/S1ACAG49/CASH WDL/17-09-23 | D22: 4 | F22: 10000 | G22: =SUM(E22:F22) -> 10000 | I22: =I21+G22 -> 123339 | J22: 45552 | P22: =P21+N22 -> 5000 | Q22: =I22-P22 -> 118339
A23: 45553 | G23: =SUM(E23:F23) -> 0 | I23: =I22+G23 -> 123339 | J23: 45553 | P23: =P22+N23 -> 5000 | Q23: =I23-P23 -> 118339
A24: 45554 | G24: =SUM(E24:F24) -> 0 | I24: =I23+G24 -> 123339 | J24: 45554 | P24: =P23+N24 -> 5000 | Q24: =I24-P24 -> 118339
A25: 45555 | G25: =SUM(E25:F25) -> 0 | I25: =I24+G25 -> 123339 | J25: 45555 | K25: Salary | L25: Gaurav | M25: 9 | N25: 3000 | P25: =P24+N25 -> 8000 | Q25: =I25-P25 -> 115339
A26: 45556 | G26: =SUM(E26:F26) -> 0 | I26: =I25+G26 -> 123339 | J26: 45556 | P26: =P25+N26 -> 8000 | Q26: =I26-P26 -> 115339
A27: 45557 | G27: =SUM(E27:F27) -> 0 | I27: =I26+G27 -> 123339 | J27: 45557 | P27: =P26+N27 -> 8000 | Q27: =I27-P27 -> 115339
A28: 45558 | G28: =SUM(E28:F28) -> 0 | I28: =I27+G28 -> 123339 | J28: 45558 | P28: =P27+N28 -> 8000 | Q28: =I28-P28 -> 115339
A29: 45559 | G29: =SUM(E29:F29) -> 0 | I29: =I28+G29 -> 123339 | J29: 45559 | P29: =P28+N29 -> 8000 | Q29: =I29-P29 -> 115339
A30: 45560 | G30: =SUM(E30:F30) -> 0 | I30: =I29+G30 -> 123339 | J30: 45560 | P30: =P29+N30 -> 8000 | Q30: =I30-P30 -> 115339
A31: 45561 | G31: =SUM(E31:F31) -> 0 | I31: =I30+G31 -> 123339 | J31: 45561 | P31: =P30+N31 -> 8000 | Q31: =I31-P31 -> 115339
A32: 45562 | G32: =SUM(E32:F32) -> 0 | I32: =I31+G32 -> 123339 | J32: 45562 | P32: =P31+N32 -> 8000 | Q32: =I32-P32 -> 115339
A33: 45563 | G33: =SUM(E33:F33) -> 0 | I33: =I32+G33 -> 123339 | J33: 45563 | K33: Veh. Exp. | L33: Petrol | M33: 11 | N33: 500 | P33: =P32+N33 -> 8500 | Q33: =I33-P33 -> 114839
A34: 45564 | G34: =SUM(E34:F34) -> 0 | I34: =I33+G34 -> 123339 | J34: 45564 | P34: =P33+N34 -> 8500 | Q34: =I34-P34 -> 114839
A35: 45565 | G35: =SUM(E35:F35) -> 0 | I35: =I34+G35 -> 123339 | J35: 45565 | K35: Balance | L35: C/F | N35: =Q34 -> 114839 | P35: =P34+N35 -> 123339 | Q35: =I35-P35 -> 0
H37: =SUM(H6:H35) -> 0 | I37: =J40+G37 -> 0 | O37: =SUM(O6:O35) -> 0

Sheet Oct
A2: CB2025-2026.xlsx | C2: Anurag-Professional | D2: Status: | E2: Individual | G2: CASHBOOK | I2: PAN: | J2: AFIPG7802B | L2: Asst.Yr. | N2: Month | O2: =CHOOSE(MONTH(A6),"Jan","Feb","Mar","Apr","May","Jun","Jul","Aug","Sep","Oct","Nov","Dec") -> Oct
A4: Date | B4: Reciept A/c | C4: Reciept Particulars | D4: L.F. No. | E4: VNH | F4: Cash | G4: Cash | H4: Chq. | I4: Total | J4: Date | K4: Payment A/c | L4: Payment Particulars | M4: L.F. No. | N4: Cash | O4: Chq. | P4: Total | Q4: Balance
A6: 45566 | B6: Balance | C6: B/F | F6: =Sep!N35 -> 114839 | G6: =Sep!N35 -> 114839 | I6: =I5+G6 -> 114839 | J6: 45566 | P6: =P5+N6 -> 0 | Q6: =I6-P6 -> 114839
A7: 45567 | G7: =SUM(E7:F7) -> 0 | I7: =I6+G7 -> 114839 | J7: 45567 | K7: Veh. Exp. | L7: Petrol | M7: 9 | N7: 1000 | P7: =P6+N7 -> 1000 | Q7: =I7-P7 -> 113839
A8: 45568 | B8: Patients | C8: TRFR FROM: SHRI MARUTINANDAN HEALTHCARE PRIVATE LI | D8: 8 | G8: =SUM(E8:F8) -> 0 | H8: =2520*1.1 -> 2772 | I8: =I7+G8 -> 114839 | J8: 45568 | K8: ICICI | L8: TRFR FROM: SHRI MARUTINANDAN HEALTHCARE PRIVATE LI | M8: 4 | O8: 2520 | P8: =P7+N8 -> 1000 | Q8: =I8-P8 -> 113839
A9: 45568 | G9: =SUM(E9:F9) -> 0 | I9: =I8+G9 -> 114839 | J9: 45568 | K9: TDStoIT | M9: 10 | O9: 252 | P9: =P8+N9 -> 1000 | Q9: =I9-P9 -> 113839
A10: 45568 | B10: Patients | C10: TRFR FROM: SHRI MARUTINANDAN HEALTHCARE PRIVATE LI | D10: 8 | G10: =SUM(E10:F10) -> 0 | H10: =5400*1.1 -> 5940 | I10: =I9+G10 -> 114839 | J10: 45568 | K10: ICICI | L10: TRFR FROM: SHRI MARUTINANDAN HEALTHCARE PRIVATE LI | M10: 4 | O10: 5400 | P10: =P9+N10 -> 1000 | Q10: =I10-P10 -> 113839
A11: 45568 | G11: =SUM(E11:F11) -> 0 | I11: =I10+G11 -> 114839 | J11: 45568 | K11: TDStoIT | M11: 10 | O11: 540 | P11: =P10+N11 -> 1000 | Q11: =I11-P11 -> 113839
A12: 45568 | B12: Patients | C12: TRFR FROM: SHRI MARUTINANDAN HEALTHCARE PRIVATE LI | D12: 8 | G12: =SUM(E12:F12) -> 0 | H12: =4140*1.1 -> 4554 | I12: =I11+G12 -> 114839 | J12: 45568 | K12: ICICI | L12: TRFR FROM: SHRI MARUTINANDAN HEALTHCARE PRIVATE LI | M12: 4 | O12: 4140 | P12: =P11+N12 -> 1000 | Q12: =I12-P12 -> 113839
A13: 45568 | G13: =SUM(E13:F13) -> 0 | I13: =I12+G13 -> 114839 | J13: 45568 | K13: TDStoIT | M13: 10 | O13: 414 | P13: =P12+N20 -> 1500 | Q13: =I13-P13 -> 113339
A14: 45574 | G14: =SUM(E14:F14) -> 0 | I14: =I13+G14 -> 114839 | J14: 45574 | P14: =P13+N21 -> 1500 | Q14: =I14-P14 -> 113339
A15: 45575 | G15: =SUM(E15:F15) -> 0 | I15: =I14+G15 -> 114839 | J15: 45575 | P15: =P14+N15 -> 1500 | Q15: =I15-P15 -> 113339
A16: 45576 | G16: =SUM(E16:F16) -> 0 | I16: =I15+G16 -> 114839 | J16: 45576 | P16: =P15+N16 -> 1500 | Q16: =I16-P16 -> 113339
A17: 45577 | G17: =SUM(E17:F17) -> 0 | I17: =I16+G17 -> 114839 | J17: 45577 | P17: =P16+N17 -> 1500 | Q17: =I17-P17 -> 113339
A18: 45578 | G18: =SUM(E18:F18) -> 0 | I18: =I17+G18 -> 114839 | J18: 45578 | P18: =P17+N18 -> 1500 | Q18: =I18-P18 -> 113339
A19: 45579 | G19: =SUM(E19:F19) -> 0 | I19: =I18+G19 -> 114839 | J19: 45579 | P19: =P18+N19 -> 1500 | Q19: =I19-P19 -> 113339
A20: 45580 | G20: =SUM(E20:F20) -> 0 | I20: =I19+G20 -> 114839 | J20: 45580 | K20: Veh. Exp. | L20: Petrol | M20: 11 | N20: 500 | P20: =P19+N20 -> 2000 | Q20: =I20-P20 -> 112839
A21: 45581 | G21: =SUM(E21:F21) -> 0 | I21: =I20+G21 -> 114839 | J21: 45581 | P21: =P20+N21 -> 2000 | Q21: =I21-P21 -> 112839
A22: 45582 | G22: =SUM(E22:F22) -> 0 | I22: =I21+G22 -> 114839 | J22: 45582 | P22: =P21+N22 -> 2000 | Q22: =I22-P22 -> 112839
A23: 45583 | G23: =SUM(E23:F23) -> 0 | I23: =I22+G23 -> 114839 | J23: 45583 | P23: =P22+N23 -> 2000 | Q23: =I23-P23 -> 112839
A24: 45584 | G24: =SUM(E24:F24) -> 0 | I24: =I23+G24 -> 114839 | J24: 45584 | P24: =P23+N24 -> 2000 | Q24: =I24-P24 -> 112839
A25: 45585 | G25: =SUM(E25:F25) -> 0 | I25: =I24+G25 -> 114839 | J25: 45585 | K25: Salary | L25: Gaurav | M25: 9 | N25: 3000 | P25: =P24+N25 -> 5000 | Q25: =I25-P25 -> 109839
A26: 45586 | G26: =SUM(E26:F26) -> 0 | I26: =I25+G26 -> 114839 | J26: 45586 | P26: =P25+N26 -> 5000 | Q26: =I26-P26 -> 109839
A27: 45587 | B27: ICICI | C27: NFS/CASH WDL/329515011779/S1ACAG49/AGRA /22-10 | D27: 4 | F27: 5000 | G27: =SUM(E27:F27) -> 5000 | I27: =I26+G27 -> 119839 | J27: 45587 | P27: =P26+N27 -> 5000 | Q27: =I27-P27 -> 114839
A28: 45588 | G28: =SUM(E28:F28) -> 0 | I28: =I27+G28 -> 119839 | J28: 45588 | P28: =P27+N28 -> 5000 | Q28: =I28-P28 -> 114839
A29: 45589 | G29: =SUM(E29:F29) -> 0 | I29: =I28+G29 -> 119839 | J29: 45589 | P29: =P28+N29 -> 5000 | Q29: =I29-P29 -> 114839
A30: 45590 | G30: =SUM(E30:F30) -> 0 | I30: =I29+G30 -> 119839 | J30: 45590 | K30: Veh. Exp. | L30: Petrol | M30: 11 | N30: 500 | P30: =P29+N30 -> 5500 | Q30: =I30-P30 -> 114339
A31: 45591 | G31: =SUM(E31:F31) -> 0 | I31: =I30+G31 -> 119839 | J31: 45591 | P31: =P30+N31 -> 5500 | Q31: =I31-P31 -> 114339
A32: 45592 | G32: =SUM(E32:F32) -> 0 | I32: =I31+G32 -> 119839 | J32: 45592 | P32: =P31+N32 -> 5500 | Q32: =I32-P32 -> 114339
A33: 45593 | G33: =SUM(E33:F33) -> 0 | I33: =I32+G33 -> 119839 | J33: 45593 | P33: =P32+N33 -> 5500 | Q33: =I33-P33 -> 114339
A34: 45594 | G34: =SUM(E34:F34) -> 0 | I34: =I33+G34 -> 119839 | J34: 45594 | P34: =P33+N34 -> 5500 | Q34: =I34-P34 -> 114339
A35: 45595 | G35: =SUM(E35:F35) -> 0 | I35: =I34+G35 -> 119839 | J35: 45595 | P35: =P34+N35 -> 5500 | Q35: =I35-P35 -> 114339
A36: 45596 | G36: =SUM(E36:F36) -> 0 | I36: =I35+G36 -> 119839 | J36: 45596 | P36: =P35+N36 -> 5500 | Q36: =I36-P36 -> 114339
A37: 45596 | G37: =SUM(E37:F37) -> 0 | I37: =I36+G37 -> 119839 | J37: 45596 | K37: Balance | L37: C/F | N37: =Q36 -> 114339 | P37: =P36+N37 -> 119839 | Q37: =I37-P37 -> 0
H39: =SUM(H6:H37) -> 13266 | O39: =SUM(O6:O37) -> 13266

Sheet Nov
A2: CB2025-2026.xlsx | C2: Anurag-Professional | D2: Status: | E2: Individual | G2: CASHBOOK | I2: PAN: | J2: AFIPG7802B | L2: Asst.Yr. | N2: Month | O2: =CHOOSE(MONTH(A6),"Jan","Feb","Mar","Apr","May","Jun","Jul","Aug","Sep","Oct","Nov","Dec") -> Nov
A4: Date | B4: Reciept A/c | C4: Reciept Particulars | D4: L.F. No. | E4: VNH | F4: Cash | G4: Cash | H4: Chq. | I4: Total | J4: Date | K4: Payment A/c | L4: Payment Particulars | M4: L.F. No. | N4: Cash | O4: Chq. | P4: Total | Q4: Balance
A6: 45597 | B6: Balance | C6: B/F | F6: =Oct!N37 -> 114339 | G6: =Oct!N37 -> 114339 | I6: =I5+G6 -> 114339 | J6: 45597 | P6: =P5+N6 -> 0 | Q6: =I6-P6 -> 114339
A7: 45598 | G7: =SUM(E7:F7) -> 0 | I7: =I6+G7 -> 114339 | J7: 45598 | P7: =P6+N7 -> 0 | Q7: =I7-P7 -> 114339
A8: 45599 | G8: =SUM(E8:F8) -> 0 | I8: =I7+G8 -> 114339 | J8: 45599 | P8: =P7+N8 -> 0 | Q8: =I8-P8 -> 114339
A9: 45600 | G9: =SUM(E9:F9) -> 0 | I9: =I8+G9 -> 114339 | J9: 45600 | K9: Salary | L9: Neeraj | M9: 9 | N9: 3000 | P9: =P8+N9 -> 3000 | Q9: =I9-P9 -> 111339
A10: 45601 | G10: =SUM(E10:F10) -> 0 | I10: =I9+G10 -> 114339 | J10: 45601 | K10: Veh. Exp. | L10: Petrol | M10: 11 | N10: 500 | P10: =P9+N10 -> 3500 | Q10: =I10-P10 -> 110839
A11: 45602 | G11: =SUM(E11:F11) -> 0 | I11: =I10+G11 -> 114339 | J11: 45602 | P11: =P10+N11 -> 3500 | Q11: =I11-P11 -> 110839
A12: 45603 | B12: Patients | C12: UPI/akjain62@unionb/fee/Union Bank of I/110003147701/UOB0056A66CAADA437F8FFB9CCF6796D6D4 | G12: =SUM(E12:F12) -> 0 | H12: 300 | I12: =I11+G12 -> 114339 | J12: 45603 | K12: ICICI | L12: UPI/akjain62@unionb/fee/Union Bank of I/110003147701/UOB0056A66CAADA437F8FFB9CCF6796D6D4 | O12: 300 | P12: =P11+N12 -> 3500 | Q12: =I12-P12 -> 110839
A13: 45604 | G13: =SUM(E13:F13) -> 0 | I13: =I12+G13 -> 114339 | J13: 45604 | P13: =P12+N13 -> 3500 | Q13: =I13-P13 -> 110839
A14: 45605 | G14: =SUM(E14:F14) -> 0 | I14: =I13+G14 -> 114339 | J14: 45605 | P14: =P13+N14 -> 3500 | Q14: =I14-P14 -> 110839
A15: 45606 | G15: =SUM(E15:F15) -> 0 | I15: =I14+G15 -> 114339 | J15: 45606 | P15: =P14+N15 -> 3500 | Q15: =I15-P15 -> 110839
A16: 45607 | G16: =SUM(E16:F16) -> 0 | I16: =I15+G16 -> 114339 | J16: 45607 | P16: =P15+N16 -> 3500 | Q16: =I16-P16 -> 110839
A17: 45608 | G17: =SUM(E17:F17) -> 0 | I17: =I16+G17 -> 114339 | J17: 45608 | P17: =P16+N17 -> 3500 | Q17: =I17-P17 -> 110839
A18: 45609 | G18: =SUM(E18:F18) -> 0 | I18: =I17+G18 -> 114339 | J18: 45609 | P18: =P17+N18 -> 3500 | Q18: =I18-P18 -> 110839
A19: 45610 | G19: =SUM(E19:F19) -> 0 | I19: =I18+G19 -> 114339 | J19: 45610 | P19: =P18+N19 -> 3500 | Q19: =I19-P19 -> 110839
A20: 45611 | G20: =SUM(E20:F20) -> 0 | I20: =I19+G20 -> 114339 | J20: 45611 | P20: =P19+N20 -> 3500 | Q20: =I20-P20 -> 110839
A21: 45612 | G21: =SUM(E21:F21) -> 0 | I21: =I20+G21 -> 114339 | J21: 45612 | P21: =P20+N21 -> 3500 | Q21: =I21-P21 -> 110839
A22: 45613 | G22: =SUM(E22:F22) -> 0 | I22: =I21+G22 -> 114339 | J22: 45613 | K22: Salary | L22: Gaurav | M22: 9 | N22: 3000 | P22: =P21+N22 -> 6500 | Q22: =I22-P22 -> 107839
A23: 45614 | D23: 5 | G23: =SUM(E23:F23) -> 0 | I23: =I22+G23 -> 114339 | J23: 45614 | K23: ICICI | P23: =P22+N23 -> 6500 | Q23: =I23-P23 -> 107839
A24: 45615 | G24: =SUM(E24:F24) -> 0 | I24: =I23+G24 -> 114339 | J24: 45615 | K24: TDStoIT | P24: =P23+N24 -> 6500 | Q24: =I24-P24 -> 107839
A25: 45616 | G25: =SUM(E25:F25) -> 0 | I25: =I24+G25 -> 114339 | J25: 45616 | P25: =P24+N25 -> 6500 | Q25: =I25-P25 -> 107839
A26: 45617 | G26: =SUM(E26:F26) -> 0 | I26: =I25+G26 -> 114339 | J26: 45617 | P26: =P25+N26 -> 6500 | Q26: =I26-P26 -> 107839
A27: 45618 | G27: =SUM(E27:F27) -> 0 | I27: =I26+G27 -> 114339 | J27: 45618 | P27: =P26+N27 -> 6500 | Q27: =I27-P27 -> 107839
A28: 45619 | G28: =SUM(E28:F28) -> 0 | I28: =I27+G28 -> 114339 | J28: 45619 | P28: =P27+N28 -> 6500 | Q28: =I28-P28 -> 107839
A29: 45620 | G29: =SUM(E29:F29) -> 0 | I29: =I28+G29 -> 114339 | J29: 45620 | P29: =P28+N29 -> 6500 | Q29: =I29-P29 -> 107839
A30: 45621 | B30: Patients | C30: TRF/SHRI MARUTINANDAN/005255/ICI/13.10.2024 | G30: =SUM(E30:F30) -> 0 | H30: =6840*1.1 -> 7524 | I30: =I29+G30 -> 114339 | J30: 45621 | K30: ICICI | L30: TRF/SHRI MARUTINANDAN/005255/ICI/13.10.2024 | O30: 6840 | P30: =P29+N30 -> 6500 | Q30: =I30-P30 -> 107839
A31: 45621 | G31: =SUM(E31:F31) -> 0 | I31: =I30+G31 -> 114339 | J31: 45621 | K31: TDStoIT | O31: 684 | P31: =P30+N31 -> 6500 | Q31: =I31-P31 -> 107839
A32: 45622 | B32: Patients | C32: CLG/SHRI MARUTI NANDAN HEAL/278319/CAB/06.11.2024 | G32: =SUM(E32:F32) -> 0 | H32: =4140*1.1 -> 4554 | I32: =I31+G32 -> 114339 | J32: 45622 | K32: ICICI | L32: CLG/SHRI MARUTI NANDAN HEAL/278319/CAB/06.11.2024 | O32: 4140 | P32: =P31+N32 -> 6500 | Q32: =I32-P32 -> 107839
A33: 45622 | G33: =SUM(E33:F33) -> 0 | I33: =I32+G33 -> 114339 | J33: 45622 | K33: TDStoIT | O33: 414 | P33: =P32+N33 -> 6500 | Q33: =I33-P33 -> 107839
A34: 45622 | B34: Patients | C34: CLG/SHRI MARUTI NANDAN HEAL/278323/CAB/06.11.2024 | G34: =SUM(E34:F34) -> 0 | H34: =4410*1.1 -> 4851 | I34: =I33+G34 -> 114339 | J34: 45622 | K34: ICICI | L34: CLG/SHRI MARUTI NANDAN HEAL/278323/CAB/06.11.2024 | O34: 4410 | P34: =P33+N34 -> 6500 | Q34: =I34-P34 -> 107839
A35: 45622 | G35: =SUM(E35:F35) -> 0 | H35: =5400*1.1 -> 5940 | I35: =I34+G35 -> 114339 | J35: 45622 | K35: TDStoIT | O35: 441 | P35: =P34+N35 -> 6500 | Q35: =I35-P35 -> 107839
A36: 45625 | B36: Patients | C36: TRF/SHRI MARUTINANDAN HEALTH/005353/ICI/20.11.2024 | G36: =SUM(E36:F36) -> 0 | I36: =I35+G36 -> 114339 | J36: 45625 | K36: ICICI | L36: TRF/SHRI MARUTINANDAN HEALTH/005353/ICI/20.11.2024 | O36: 5400 | P36: =P35+N36 -> 6500 | Q36: =I36-P36 -> 107839
A37: 45625 | G37: =SUM(E37:F37) -> 0 | I37: =I36+G37 -> 114339 | J37: 45625 | K37: TDStoIT | O37: 540 | P37: =P36+N37 -> 6500 | Q37: =I37-P37 -> 107839
A38: 45626 | G38: =SUM(E38:F38) -> 0 | I38: =I37+G38 -> 114339 | J38: 45626 | P38: =P37+N38 -> 6500 | Q38: =I38-P38 -> 107839
A39: 45626 | G39: =SUM(E39:F39) -> 0 | I39: =I38+G39 -> 114339 | J39: 45626 | P39: =P38+N39 -> 6500 | Q39: =I39-P39 -> 107839
A40: 45626 | G40: =SUM(E40:F40) -> 0 | I40: =I39+G40 -> 114339 | J40: 45626 | K40: Balance | L40: C/F | N40: =Q39 -> 107839 | P40: =P39+N40 -> 114339 | Q40: =I40-P40 -> 0
H41: =SUM(H6:H39) -> 23169 | O41: =SUM(O6:O39) -> 23169

Sheet Dec
A2: CB2025-2026.xlsx | C2: Anurag-Professional | D2: Status: | E2: Individual | G2: CASHBOOK | I2: PAN: | J2: AFIPG7802B | L2: Asst.Yr. | N2: Month | O2: =CHOOSE(MONTH(A6),"Jan","Feb","Mar","Apr","May","Jun","Jul","Aug","Sep","Oct","Nov","Dec") -> Dec
A4: Date | B4: Reciept A/c | C4: Reciept Particulars | D4: L.F. No. | E4: VNH | F4: Cash | G4: Cash | H4: Chq. | I4: Total | J4: Date | K4: Payment A/c | L4: Payment Particulars | M4: L.F. No. | N4: Cash | O4: Chq. | P4: Total | Q4: Balance
A6: 45627 | B6: Balance | C6: B/F | F6: =Nov!N40 -> 107839 | G6: =Nov!N40 -> 107839 | I6: =I5+G6 -> 107839 | J6: 45627 | P6: =P5+N6 -> 0 | Q6: =I6-P6 -> 107839
A7: 45628 | G7: =SUM(E7:F7) -> 0 | I7: =I6+G7 -> 107839 | J7: 45628 | K7: Salary | L7: Neeraj | M7: 9 | N7: 3000 | P7: =P6+N7 -> 3000 | Q7: =I7-P7 -> 104839
A8: 45629 | G8: =SUM(E8:F8) -> 0 | I8: =I7+G8 -> 107839 | J8: 45629 | P8: =P7+N8 -> 3000 | Q8: =I8-P8 -> 104839
A9: 45630 | G9: =SUM(E9:F9) -> 0 | I9: =I8+G9 -> 107839 | J9: 45630 | P9: =P8+N9 -> 3000 | Q9: =I9-P9 -> 104839
A10: 45631 | G10: =SUM(E10:F10) -> 0 | I10: =I9+G10 -> 107839 | J10: 45631 | P10: =P9+N10 -> 3000 | Q10: =I10-P10 -> 104839
A11: 45632 | G11: =SUM(E11:F11) -> 0 | I11: =I10+G11 -> 107839 | J11: 45632 | P11: =P10+N11 -> 3000 | Q11: =I11-P11 -> 104839
A12: 45633 | G12: =SUM(E12:F12) -> 0 | I12: =I11+G12 -> 107839 | J12: 45633 | P12: =P11+N12 -> 3000 | Q12: =I12-P12 -> 104839
A13: 45634 | G13: =SUM(E13:F13) -> 0 | I13: =I12+G13 -> 107839 | J13: 45634 | P13: =P12+N13 -> 3000 | Q13: =I13-P13 -> 104839
A14: 45635 | G14: =SUM(E14:F14) -> 0 | I14: =I13+G14 -> 107839 | J14: 45635 | P14: =P13+N14 -> 3000 | Q14: =I14-P14 -> 104839
A15: 45636 | G15: =SUM(E15:F15) -> 0 | I15: =I14+G15 -> 107839 | J15: 45636 | P15: =P14+N15 -> 3000 | Q15: =I15-P15 -> 104839
A16: 45637 | G16: =SUM(E16:F16) -> 0 | I16: =I15+G16 -> 107839 | J16: 45637 | P16: =P15+N16 -> 3000 | Q16: =I16-P16 -> 104839
A17: 45638 | G17: =SUM(E17:F17) -> 0 | I17: =I16+G17 -> 107839 | J17: 45638 | P17: =P16+N17 -> 3000 | Q17: =I17-P17 -> 104839
A18: 45639 | G18: =SUM(E18:F18) -> 0 | I18: =I17+G18 -> 107839 | J18: 45639 | P18: =P17+N18 -> 3000 | Q18: =I18-P18 -> 104839
A19: 45640 | G19: =SUM(E19:F19) -> 0 | I19: =I18+G19 -> 107839 | J19: 45640 | P19: =P18+N19 -> 3000 | Q19: =I19-P19 -> 104839
A20: 45641 | G20: =SUM(E20:F20) -> 0 | I20: =I19+G20 -> 107839 | J20: 45641 | P20: =P19+N20 -> 3000 | Q20: =I20-P20 -> 104839
A21: 45642 | B21: Patients | C21: UPI/aradhanajain.77/fee/UNION BANK OF I/110004731698/UOBbb6b2e4e029846c0893e0022c618aa17 | G21: =SUM(E21:F21) -> 0 | H21: 300 | I21: =I20+G21 -> 107839 | J21: 45642 | K21: ICICI | L21: UPI/aradhanajain.77/fee/UNION BANK OF I/110004731698/UOBbb6b2e4e029846c0893e0022c618aa17 | O21: 300 | P21: =P20+N21 -> 3000 | Q21: =I21-P21 -> 104839
A22: 45643 | G22: =SUM(E22:F22) -> 0 | I22: =I21+G22 -> 107839 | J22: 45643 | P22: =P21+N22 -> 3000 | Q22: =I22-P22 -> 104839
A23: 45644 | G23: =SUM(E23:F23) -> 0 | I23: =I22+G23 -> 107839 | J23: 45644 | P23: =P22+N23 -> 3000 | Q23: =I23-P23 -> 104839
A24: 45645 | G24: =SUM(E24:F24) -> 0 | I24: =I23+G24 -> 107839 | J24: 45645 | P24: =P23+N24 -> 3000 | Q24: =I24-P24 -> 104839
A25: 45646 | G25: =SUM(E25:F25) -> 0 | I25: =I24+G25 -> 107839 | J25: 45646 | P25: =P24+N25 -> 3000 | Q25: =I25-P25 -> 104839
A26: 45647 | G26: =SUM(E26:F26) -> 0 | I26: =I25+G26 -> 107839 | J26: 45647 | K26: Salary | L26: Gaurav | M26: 9 | N26: 3000 | P26: =P25+N26 -> 6000 | Q26: =I26-P26 -> 101839
A27: 45648 | G27: =SUM(E27:F27) -> 0 | I27: =I26+G27 -> 107839 | J27: 45648 | P27: =P26+N27 -> 6000 | Q27: =I27-P27 -> 101839
A28: 45649 | G28: =SUM(E28:F28) -> 0 | I28: =I27+G28 -> 107839 | J28: 45649 | P28: =P27+N28 -> 6000 | Q28: =I28-P28 -> 101839
A29: 45650 | G29: =SUM(E29:F29) -> 0 | I29: =I28+G29 -> 107839 | J29: 45650 | P29: =P28+N29 -> 6000 | Q29: =I29-P29 -> 101839
A30: 45651 | G30: =SUM(E30:F30) -> 0 | I30: =I29+G30 -> 107839 | J30: 45651 | P30: =P29+N30 -> 6000 | Q30: =I30-P30 -> 101839
A31: 45652 | B31: Patients | C31: UPI/aradhanajain.77/fee/UNION BANK OF I/110005115377/UOB8b5a3fb3b56040ac9f1cb2856b871638 | D31: 8 | G31: =SUM(E31:F31) -> 0 | H31: 300 | I31: =I30+G31 -> 107839 | J31: 45652 | K31: ICICI | L31: UPI/aradhanajain.77/fee/UNION BANK OF I/110005115377/UOB8b5a3fb3b56040ac9f1cb2856b871638 | M31: 4 | O31: 300 | P31: =P30+N31 -> 6000 | Q31: =I31-P31 -> 101839
A32: 45653 | G32: =SUM(E32:F32) -> 0 | I32: =I31+G32 -> 107839 | J32: 45653 | P32: =P31+N32 -> 6000 | Q32: =I32-P32 -> 101839
A33: 45654 | G33: =SUM(E33:F33) -> 0 | I33: =I32+G33 -> 107839 | J33: 45654 | K33: Veh. Exp. | L33: Petrol | M33: 11 | N33: 500 | P33: =P32+N33 -> 6500 | Q33: =I33-P33 -> 101339
A34: 45655 | G34: =SUM(E34:F34) -> 0 | I34: =I33+G34 -> 107839 | J34: 45655 | P34: =P33+N34 -> 6500 | Q34: =I34-P34 -> 101339
A35: 45656 | B35: ICICI | C35: NFS/CASH WDL/336315013194/S1ACAG49/AGRA /29-12 | D35: 4 | F35: 10000 | G35: =SUM(E35:F35) -> 10000 | I35: =I34+G35 -> 117839 | J35: 45656 | P35: =P34+N35 -> 6500 | Q35: =I35-P35 -> 111339
A36: 45657 | G36: =SUM(E36:F36) -> 0 | I36: =I35+G36 -> 117839 | J36: 45657 | P36: =P35+N36 -> 6500 | Q36: =I36-P36 -> 111339
A37: 45657 | G37: =SUM(E37:F37) -> 0 | I37: =I36+G37 -> 117839 | J37: 45657 | K37: Balance | L37: C/F | N37: =Q36 -> 111339 | P37: =P36+N37 -> 117839 | Q37: =I37-P37 -> 0
H39: =SUM(H6:H38) -> 600 | O39: =SUM(O6:O38) -> 600

Sheet Jan
A2: CB2025-2026.xlsx | C2: Anurag-Professional | D2: Status: | E2: Individual | G2: CASHBOOK | I2: PAN: | J2: AFIPG7802B | L2: Asst.Yr. | N2: Month | O2: =CHOOSE(MONTH(A6),"Jan","Feb","Mar","Apr","May","Jun","Jul","Aug","Sep","Oct","Nov","Dec") -> Jan
A4: Date | B4: Reciept A/c | C4: Reciept Particulars | D4: L.F. No. | E4: VNH | F4: Cash | G4: Cash | H4: Chq. | I4: Total | J4: Date | K4: Payment A/c | L4: Payment Particulars | M4: L.F. No. | N4: Cash | O4: Chq. | P4: Total | Q4: Balance
A6: 45658 | B6: Balance | C6: B/F | F6: =Dec!N37 -> 111339 | G6: =Dec!N37 -> 111339 | I6: =I5+G6 -> 111339 | J6: 45658 | P6: =P5+N6 -> 0 | Q6: =I6-P6 -> 111339
A7: 45659 | G7: =SUM(E7:F7) -> 0 | I7: =I6+G7 -> 111339 | J7: 45659 | K7: Salary | L7: Neeraj | M7: 9 | N7: 3000 | P7: =P6+N7 -> 3000 | Q7: =I7-P7 -> 108339
A8: 45660 | B8: Patients | C8: CLG/SHRI MARUTI NANDAN HEAL/278417/CAB/18.12.2024 | G8: =SUM(E8:F8) -> 0 | H8: =4680*1.1 -> 5148 | I8: =I7+G8 -> 111339 | J8: 45660 | K8: ICICI | L8: CLG/SHRI MARUTI NANDAN HEAL/278417/CAB/18.12.2024 | O8: 4680 | P8: =P7+N8 -> 3000 | Q8: =I8-P8 -> 108339
A9: 45660 | G9: =SUM(E9:F9) -> 0 | I9: =I8+G9 -> 111339 | J9: 45660 | K9: TDStoIT | O9: 468 | P9: =P8+N9 -> 3000 | Q9: =I9-P9 -> 108339
A10: 45662 | G10: =SUM(E10:F10) -> 0 | I10: =I9+G10 -> 111339 | J10: 45662 | P10: =P9+N10 -> 3000 | Q10: =I10-P10 -> 108339
A11: 45663 | G11: =SUM(E11:F11) -> 0 | I11: =I10+G11 -> 111339 | J11: 45663 | P11: =P10+N11 -> 3000 | Q11: =I11-P11 -> 108339
A12: 45664 | G12: =SUM(E12:F12) -> 0 | I12: =I11+G12 -> 111339 | J12: 45664 | P12: =P11+N12 -> 3000 | Q12: =I12-P12 -> 108339
A13: 45665 | G13: =SUM(E13:F13) -> 0 | I13: =I12+G13 -> 111339 | J13: 45665 | P13: =P12+N13 -> 3000 | Q13: =I13-P13 -> 108339
A14: 45666 | G14: =SUM(E14:F14) -> 0 | I14: =I13+G14 -> 111339 | J14: 45666 | P14: =P13+N14 -> 3000 | Q14: =I14-P14 -> 108339
A15: 45667 | G15: =SUM(E15:F15) -> 0 | I15: =I14+G15 -> 111339 | J15: 45667 | P15: =P14+N15 -> 3000 | Q15: =I15-P15 -> 108339
A16: 45668 | G16: =SUM(E16:F16) -> 0 | I16: =I15+G16 -> 111339 | J16: 45668 | P16: =P15+N16 -> 3000 | Q16: =I16-P16 -> 108339
A17: 45669 | G17: =SUM(E17:F17) -> 0 | I17: =I16+G17 -> 111339 | J17: 45669 | P17: =P16+N17 -> 3000 | Q17: =I17-P17 -> 108339
A18: 45670 | G18: =SUM(E18:F18) -> 0 | I18: =I17+G18 -> 111339 | J18: 45670 | P18: =P17+N18 -> 3000 | Q18: =I18-P18 -> 108339
A19: 45671 | G19: =SUM(E19:F19) -> 0 | I19: =I18+G19 -> 111339 | J19: 45671 | P19: =P18+N19 -> 3000 | Q19: =I19-P19 -> 108339
A20: 45672 | G20: =SUM(E20:F20) -> 0 | I20: =I19+G20 -> 111339 | J20: 45672 | P20: =P19+N20 -> 3000 | Q20: =I20-P20 -> 108339
A21: 45673 | G21: =SUM(E21:F21) -> 0 | I21: =I20+G21 -> 111339 | J21: 45673 | P21: =P20+N21 -> 3000 | Q21: =I21-P21 -> 108339
... A24: 45676 | G24: =SUM(E24:F24) -> 0 | I24: =I23+G24 -> 111339 | J24: 45676 | P24: =P23+N24 -> 3000 | Q24: =I24-P24 -> 108339
A25: 45677 | G25: =SUM(E25:F25) -> 0 | I25: =I24+G25 -> 111339 | J25: 45677 | K25: Salary | L25: Gaurav | M25: 9 | N25: 3000 | P25: =P24+N25 -> 6000 | Q25: =I25-P25 -> 105339
A26: 45678 | G26: =SUM(E26:F26) -> 0 | I26: =I25+G26 -> 111339 | J26: 45678 | P26: =P25+N26 -> 6000 | Q26: =I26-P26 -> 105339
A27: 45679 | G27: =SUM(E27:F27) -> 0 | I27: =I26+G27 -> 111339 | J27: 45679 | K27: Veh. Exp. | L27: Petrol | M27: 11 | N27: 500 | P27: =P26+N27 -> 6500 | Q27: =I27-P27 -> 104839
A28: 45680 | G28: =SUM(E28:F28) -> 0 | I28: =I27+G28 -> 111339 | J28: 45680 | P28: =P27+N28 -> 6500 | Q28: =I28-P28 -> 104839
A29: 45681 | B29: Patients | C29: TRF/SHRI MURTINANDAN HWEALT/004311/ICI/05.01.2024 | D29: 8 | G29: =SUM(E29:F29) -> 0 | H29: 9600 | I29: =I28+G29 -> 111339 | J29: 45681 | K29: ICICI | L29: TRF/SHRI MURTINANDAN HWEALT/004311/ICI/05.01.2024 | M29: 4 | O29: 8640 | P29: =P28+N29 -> 6500 | Q29: =I29-P29 -> 104839
A30: 45682 | G30: =SUM(E30:F30) -> 0 | I30: =I29+G30 -> 111339 | J30: 45682 | K30: TDStoIT | M30: 10 | O30: 960 | P30: =P29+N30 -> 6500 | Q30: =I30-P30 -> 104839
A31: 45683 | B31: ICICI | C31: NFS/CASH WDL/402522024752/S1ACAG49/AGRA /25-01 | D31: 4 | F31: 10000 | G31: =SUM(E31:F31) -> 10000 | I31: =I30+G31 -> 121339 | J31: 45683 | P31: =P30+N31 -> 6500 | Q31: =I31-P31 -> 114839
A32: 45684 | G32: =SUM(E32:F32) -> 0 | I32: =I31+G32 -> 121339 | J32: 45684 | P32: =P31+N32 -> 6500 | Q32: =I32-P32 -> 114839
A33: 45685 | G33: =SUM(E33:F33) -> 0 | I33: =I32+G33 -> 121339 | J33: 45685 | P33: =P32+N33 -> 6500 | Q33: =I33-P33 -> 114839
A34: 45686 | G34: =SUM(E34:F34) -> 0 | I34: =I33+G34 -> 121339 | J34: 45686 | P34: =P33+N34 -> 6500 | Q34: =I34-P34 -> 114839
A35: 45687 | G35: =SUM(E35:F35) -> 0 | I35: =I34+G35 -> 121339 | J35: 45687 | P35: =P34+N35 -> 6500 | Q35: =I35-P35 -> 114839
A36: 45688 | G36: =SUM(E36:F36) -> 0 | I36: =I35+G36 -> 121339 | J36: 45688 | K36: Balance | L36: C/F | N36: =Q35 -> 114839 | P36: =P35+N36 -> 121339 | Q36: =I36-P36 -> 0
A37: 45688 | J37: 45688
H39: =SUM(H6:H36) -> 14748 | O39: =SUM(O6:O36) -> 14748

Sheet Feb
A2: CB2025-2026.xlsx | C2: Anurag-Professional | D2: Status: | E2: Individual | G2: CASHBOOK | I2: PAN: | J2: AFIPG7802B | L2: Asst.Yr. | N2: Month | O2: =CHOOSE(MONTH(A6),"Jan","Feb","Mar","Apr","May","Jun","Jul","Aug","Sep","Oct","Nov","Dec") -> Feb
A4: Date | B4: Reciept A/c | C4: Reciept Particulars | D4: L.F. No. | E4: VNH | F4: Cash | G4: Cash | H4: Chq. | I4: Total | J4: Date | K4: Payment A/c | L4: Payment Particulars | M4: L.F. No. | N4: Cash | O4: Chq. | P4: Total | Q4: Balance
A6: 45689 | B6: Balance | C6: B/F | F6: =Jan!N36 -> 114839 | G6: =Jan!N36 -> 114839 | I6: =I5+G6 -> 114839 | J6: 45689 | P6: =P5+N6 -> 0 | Q6: =I6-P6 -> 114839
A7: 45690 | G7: =SUM(E7:F7) -> 0 | I7: =I6+G7 -> 114839 | J7: 45690 | K7: Salary | L7: Neeraj | M7: 9 | N7: 3000 | P7: =P6+N7 -> 3000 | Q7: =I7-P7 -> 111839
A8: 45691 | G8: =SUM(E8:F8) -> 0 | I8: =I7+G8 -> 114839 | J8: 45691 | P8: =P7+N8 -> 3000 | Q8: =I8-P8 -> 111839
A9: 45692 | G9: =SUM(E9:F9) -> 0 | I9: =I8+G9 -> 114839 | J9: 45692 | P9: =P8+N9 -> 3000 | Q9: =I9-P9 -> 111839
A10: 45693 | B10: Patients | C10: UPI/avneshjain.agra/UPI/UNION BANK OF I/540232791818/ICI0f58808fdff34a76848506c81c218908 | G10: =SUM(E10:F10) -> 0 | H10: 300 | I10: =I9+G10 -> 114839 | J10: 45693 | K10: ICICI | L10: UPI/avneshjain.agra/UPI/UNION BANK OF I/540232791818/ICI0f58808fdff34a76848506c81c218908 | M10: 11 | O10: 300 | P10: =P9+N10 -> 3000 | Q10: =I10-P10 -> 111839
A11: 45694 | G11: =SUM(E11:F11) -> 0 | I11: =I10+G11 -> 114839 | J11: 45694 | P11: =P10+N11 -> 3000 | Q11: =I11-P11 -> 111839
A12: 45695 | G12: =SUM(E12:F12) -> 0 | I12: =I11+G12 -> 114839 | J12: 45695 | P12: =P11+N12 -> 3000 | Q12: =I12-P12 -> 111839
A13: 45696 | G13: =SUM(E13:F13) -> 0 | I13: =I12+G13 -> 114839 | J13: 45696 | P13: =P12+N13 -> 3000 | Q13: =I13-P13 -> 111839
A14: 45697 | G14: =SUM(E14:F14) -> 0 | I14: =I13+G14 -> 114839 | J14: 45697 | P14: =P13+N14 -> 3000 | Q14: =I14-P14 -> 111839
A15: 45698 | I15: =I14+G15 -> 114839 | J15: 45698 | P15: =P14+N15 -> 3000 | Q15: =I15-P15 -> 111839
A16: 45699 | G16: =SUM(E16:F16) -> 0 | I16: =I15+G16 -> 114839 | J16: 45699 | P16: =P15+N16 -> 3000 | Q16: =I16-P16 -> 111839
A17: 45700 | G17: =SUM(E17:F17) -> 0 | I17: =I16+G17 -> 114839 | J17: 45700 | P17: =P16+N17 -> 3000 | Q17: =I17-P17 -> 111839
A18: 45701 | B18: Patients | C18: TRF/SHRI MARUTINANDAN/005591/ICI/04.02.2025 | G18: =SUM(E18:F18) -> 0 | H18: =41130*1.1 -> 45243 | I18: =I17+G18 -> 114839 | J18: 45701 | K18: ICICI | L18: TRF/SHRI MARUTINANDAN/005591/ICI/04.02.2025 | O18: 41130 | P18: =P17+N18 -> 3000 | Q18: =I18-P18 -> 111839
A19: 45701 | G19: =SUM(E19:F19) -> 0 | I19: =I18+G19 -> 114839 | J19: 45701 | K19: TDStoIT | O19: 4113 | P19: =P18+N19 -> 3000 | Q19: =I19-P19 -> 111839
A20: 45703 | B20: ICICI | C20: ATM/S1CNQ071/CASH WDL/13-02-24 | D20: 4 | F20: 10000 | G20: =SUM(E20:F20) -> 10000 | I20: =I19+G20 -> 124839 | J20: 45703 | P20: =P19+N20 -> 3000 | Q20: =I20-P20 -> 121839
A21: 45704 | G21: =SUM(E21:F21) -> 0 | I21: =I20+G21 -> 124839 | J21: 45704 | P21: =P20+N21 -> 3000 | Q21: =I21-P21 -> 121839
A22: 45705 | G22: =SUM(E22:F22) -> 0 | I22: =I21+G22 -> 124839 | J22: 45705 | P22: =P21+N22 -> 3000 | Q22: =I22-P22 -> 121839
A23: 45706 | G23: =SUM(E23:F23) -> 0 | I23: =I22+G23 -> 124839 | J23: 45706 | P23: =P22+N23 -> 3000 | Q23: =I23-P23 -> 121839
A24: 45707 | G24: =SUM(E24:F24) -> 0 | I24: =I23+G24 -> 124839 | J24: 45707 | P24: =P23+N24 -> 3000 | Q24: =I24-P24 -> 121839
A25: 45708 | G25: =SUM(E25:F25) -> 0 | I25: =I24+G25 -> 124839 | J25: 45708 | P25: =P24+N25 -> 3000 | Q25: =I25-P25 -> 121839
A26: 45709 | G26: =SUM(E26:F26) -> 0 | I26: =I25+G26 -> 124839 | J26: 45709 | P26: =P25+N26 -> 3000 | Q26: =I26-P26 -> 121839
A27: 45710 | G27: =SUM(E27:F27) -> 0 | I27: =I26+G27 -> 124839 | J27: 45710 | P27: =P26+N27 -> 3000 | Q27: =I27-P27 -> 121839
A28: 45711 | G28: =SUM(E28:F28) -> 0 | I28: =I27+G28 -> 124839 | J28: 45711 | K28: Salary | L28: Gaurav | M28: 9 | N28: 3000 | P28: =P27+N28 -> 6000 | Q28: =I28-P28 -> 118839
A29: 45712 | G29: =SUM(E29:F29) -> 0 | I29: =I28+G29 -> 124839 | J29: 45712 | P29: =P28+N29 -> 6000 | Q29: =I29-P29 -> 118839
A30: 45713 | G30: =SUM(E30:F30) -> 0 | I30: =I29+G30 -> 124839 | J30: 45713 | P30: =P29+N30 -> 6000 | Q30: =I30-P30 -> 118839
A31: 45714 | G31: =SUM(E31:F31) -> 0 | I31: =I30+G31 -> 124839 | J31: 45714 | P31: =P30+N31 -> 6000 | Q31: =I31-P31 -> 118839
A32: 45715 | G32: =SUM(E32:F32) -> 0 | I32: =I31+G32 -> 124839 | J32: 45715 | P32: =P31+N32 -> 6000 | Q32: =I32-P32 -> 118839
A33: 45716 | G33: =SUM(E33:F33) -> 0 | I33: =I32+G33 -> 124839 | J33: 45716 | P33: =P32+N33 -> 6000 | Q33: =I33-P33 -> 118839
A34: 45716 | G34: =SUM(E34:F34) -> 0 | I34: =I33+G34 -> 124839 | J34: 45716 | P34: =P33+N34 -> 6000 | Q34: =I34-P34 -> 118839
A35: 45716 | G35: =SUM(E35:F35) -> 0 | I35: =I34+G35 -> 124839 | J35: 45716 | P35: =P34+N35 -> 6000 | Q35: =I35-P35 -> 118839
A36: 45716 | J36: 45716
A37: 45716 | G37: =SUM(E37:F37) -> 0 | I37: =I35+G37 -> 124839 | J37: 45716 | P37: =P35+N36 -> 6000 | Q37: =I37-P37 -> 118839
A38: 45716 | G38: =SUM(E38:F38) -> 0 | I38: =I37+G38 -> 124839 | J38: 45716 | P38: =P37+N38 -> 6000 | Q38: =I38-P38 -> 118839
A39: 45716 | G39: =SUM(E39:F39) -> 0 | I39: =I38+G39 -> 124839 | J39: 45716 | P39: =P38+N39 -> 6000 | Q39: =I39-P39 -> 118839
A40: 45716 | G40: =SUM(E40:F40) -> 0 | I40: =I39+G40 -> 124839 | J40: 45716 | P40: =P39+N40 -> 6000 | Q40: =I40-P40 -> 118839
A41: 45716 | G41: =SUM(E41:F41) -> 0 | I41: =I40+G41 -> 124839 | J41: 45716 | P41: =P40+N41 -> 6000 | Q41: =I41-P41 -> 118839
A42: 45716 | G42: =SUM(E42:F42) -> 0 | I42: =I41+G42 -> 124839 | J42: 45716 | P42: =P41+N42 -> 6000 | Q42: =I42-P42 -> 118839
A43: 45716 | G43: =SUM(E43:F43) -> 0 | I43: =I42+G43 -> 124839 | J43: 45716 | K43: Balance | L43: C/F | N43: =Q42 -> 118839 | P43: =P42+N43 -> 124839 | Q43: =I43-P43 -> 0
H45: =SUM(H6:H43) -> 45543 | O45: =SUM(O6:O43) -> 45543

Sheet Mar
A2: CB2025-2026.xlsx | C2: Anurag-Professional | D2: Status: | E2: Individual | G2: CASHBOOK | I2: PAN: | J2: AFIPG7802B | L2: Asst.Yr. | N2: Month | O2: =CHOOSE(MONTH(A6),"Jan","Feb","Mar","Apr","May","Jun","Jul","Aug","Sep","Oct","Nov","Dec") -> Mar
A4: Date | B4: Reciept A/c | C4: Reciept Particulars | D4: L.F. No. | E4: VNH | F4: Cash | G4: Cash | H4: Chq. | I4: Total | J4: Date | K4: Payment A/c | L4: Payment Particulars | M4: L.F. No. | N4: Cash | O4: Chq. | P4: Total | Q4: Balance
A6: 45717 | B6: Balance | C6: B/F | F6: =Feb!N43 -> 118839 | G6: =Feb!N43 -> 118839 | I6: =I5+G6 -> 118839 | J6: 45717 | P6: =P5+N6 -> 0 | Q6: =I6-P6 -> 118839
A7: 45718 | G7: =SUM(E7:F7) -> 0 | I7: =I6+G7 -> 118839 | J7: 45718 | K7: Salary | L7: Neeraj | M7: 9 | N7: 3000 | P7: =P6+N7 -> 3000 | Q7: =I7-P7 -> 115839
A8: 45719 | G8: =SUM(E8:F8) -> 0 | I8: =I7+G8 -> 118839 | J8: 45719 | P8: =P7+N8 -> 3000 | Q8: =I8-P8 -> 115839
A9: 45720 | B9: Patients | C9: TRF/SHRI MARUTINANDAN/004572/ICI/25.02.2024 | D9: 8 | G9: =SUM(E9:F9) -> 0 | H9: 2700 | I9: =I8+G9 -> 118839 | J9: 45720 | K9: ICICI | L9: TRF/SHRI MARUTINANDAN/004572/ICI/25.02.2024 | M9: 4 | O9: 2430 | P9: =P8+N9 -> 3000 | Q9: =I9-P9 -> 115839
A10: 45721 | G10: =SUM(E10:F10) -> 0 | I10: =I9+G10 -> 118839 | J10: 45721 | K10: TDStoIT | M10: 10 | O10: 270 | P10: =P9+N10 -> 3000 | Q10: =I10-P10 -> 115839
A11: 45722 | G11: =SUM(E11:F11) -> 0 | I11: =I10+G11 -> 118839 | J11: 45722 | P11: =P10+N11 -> 3000 | Q11: =I11-P11 -> 115839
A12: 45723 | G12: =SUM(E12:F12) -> 0 | I12: =I11+G12 -> 118839 | J12: 45723 | P12: =P11+N12 -> 3000 | Q12: =I12-P12 -> 115839
A13: 45724 | G13: =SUM(E13:F13) -> 0 | I13: =I12+G13 -> 118839 | J13: 45724 | P13: =P12+N13 -> 3000 | Q13: =I13-P13 -> 115839
A14: 45725 | G14: =SUM(E14:F14) -> 0 | I14: =I13+G14 -> 118839 | J14: 45725 | K14: Veh. Exp. | L14: Petrol | M14: 11 | N14: 500 | P14: =P13+N14 -> 3500 | Q14: =I14-P14 -> 115339
A15: 45726 | G15: =SUM(E15:F15) -> 0 | I15: =I14+G15 -> 118839 | J15: 45726 | P15: =P14+N15 -> 3500 | Q15: =I15-P15 -> 115339
A16: 45727 | G16: =SUM(E16:F16) -> 0 | I16: =I15+G16 -> 118839 | J16: 45727 | P16: =P15+N16 -> 3500 | Q16: =I16-P16 -> 115339
A17: 45728 | G17: =SUM(E17:F17) -> 0 | I17: =I16+G17 -> 118839 | J17: 45728 | P17: =P16+N17 -> 3500 | Q17: =I17-P17 -> 115339
A18: 45729 | G18: =SUM(E18:F18) -> 0 | I18: =I17+G18 -> 118839 | J18: 45729 | P18: =P17+N18 -> 3500 | Q18: =I18-P18 -> 115339
A19: 45730 | G19: =SUM(E19:F19) -> 0 | I19: =I18+G19 -> 118839 | J19: 45730 | P19: =P18+N19 -> 3500 | Q19: =I19-P19 -> 115339
A20: 45731 | G20: =SUM(E20:F20) -> 0 | I20: =I19+G20 -> 118839 | J20: 45731 | P20: =P19+N20 -> 3500 | Q20: =I20-P20 -> 115339
A21: 45732 | B21: Patients | C21: TRFR FROM:SHRI MARUTINANDAN HEALTHCARE PRIVATE LIM | D21: 8 | G21: =SUM(E21:F21) -> 0 | H21: 3200 | I21: =I20+G21 -> 118839 | J21: 45732 | K21: ICICI | L21: TRFR FROM:SHRI MARUTINANDAN HEALTHCARE PRIVATE LIM | M21: 4 | O21: 2880 | P21: =P20+N21 -> 3500 | Q21: =I21-P21 -> 115339
A22: 45733 | B22: ICICI | C22: NFS/CASH WDL/407521989689/UN224601/AGRA /15-03 | D22: 4 | F22: 10000 | G22: =SUM(E22:F22) -> 10000 | I22: =I21+G22 -> 128839 | J22: 45733 | K22: TDStoIT | M22: 10 | O22: 320 | P22: =P21+N22 -> 3500 | Q22: =I22-P22 -> 125339
A23: 45734 | G23: =SUM(E23:F23) -> 0 | I23: =I22+G23 -> 128839 | J23: 45734 | P23: =P22+N23 -> 3500 | Q23: =I23-P23 -> 125339
A24: 45735 | G24: =SUM(E24:F24) -> 0 | I24: =I23+G24 -> 128839 | J24: 45735 | P24: =P23+N24 -> 3500 | Q24: =I24-P24 -> 125339
A25: 45736 | G25: =SUM(E25:F25) -> 0 | I25: =I24+G25 -> 128839 | J25: 45736 | K25: Salary | L25: Gaurav | M25: 9 | N25: 3000 | P25: =P24+N25 -> 6500 | Q25: =I25-P25 -> 122339
A26: 45737 | G26: =SUM(E26:F26) -> 0 | I26: =I25+G26 -> 128839 | J26: 45737 | P26: =P25+N26 -> 6500 | Q26: =I26-P26 -> 122339
A27: 45738 | G27: =SUM(E27:F27) -> 0 | I27: =I26+G27 -> 128839 | J27: 45738 | P27: =P26+N27 -> 6500 | Q27: =I27-P27 -> 122339
A28: 45739 | G28: =SUM(E28:F28) -> 0 | I28: =I27+G28 -> 128839 | J28: 45739 | P28: =P27+N28 -> 6500 | Q28: =I28-P28 -> 122339
A29: 45740 | G29: =SUM(E29:F29) -> 0 | I29: =I28+G29 -> 128839 | J29: 45740 | P29: =P28+N29 -> 6500 | Q29: =I29-P29 -> 122339
A30: 45741 | G30: =SUM(E30:F30) -> 0 | I30: =I29+G30 -> 128839 | J30: 45741 | P30: =P29+N30 -> 6500 | Q30: =I30-P30 -> 122339
A31: 45742 | G31: =SUM(E31:F31) -> 0 | I31: =I30+G31 -> 128839 | J31: 45742 | P31: =P30+N31 -> 6500 | Q31: =I31-P31 -> 122339
A32: 45743 | G32: =SUM(E32:F32) -> 0 | I32: =I31+G32 -> 128839 | J32: 45743 | P32: =P31+N32 -> 6500 | Q32: =I32-P32 -> 122339
A33: 45744 | G33: =SUM(E33:F33) -> 0 | I33: =I32+G33 -> 128839 | J33: 45744 | P33: =P32+N33 -> 6500 | Q33: =I33-P33 -> 122339
A34: 45745 | G34: =SUM(E34:F34) -> 0 | I34: =I33+G34 -> 128839 | J34: 45745 | K34: Veh. Exp. | L34: Petrol | M34: 11 | N34: 500 | P34: =P33+N34 -> 7000 | Q34: =I34-P34 -> 121839
A35: 45746 | G35: =SUM(E35:F35) -> 0 | I35: =I34+G35 -> 128839 | J35: 45746 | P35: =P34+N35 -> 7000 | Q35: =I35-P35 -> 121839
A36: 45747 | G36: =SUM(E36:F36) -> 0 | I36: =I35+G36 -> 128839 | J36: 45747 | P36: =P35+N36 -> 7000 | Q36: =I36-P36 -> 121839
A37: 45747 | G37: =SUM(E37:F37) -> 0 | I37: =I36+G37 -> 128839 | J37: 45747 | P37: =P36+N37 -> 7000 | Q37: =I37-P37 -> 121839
A38: 45747 | G38: =SUM(E38:F38) -> 0 | I38: =I37+G38 -> 128839 | J38: 45747 | K38: Balance | L38: C/F | N38: =Q37 -> 121839 | P38: =P37+N38 -> 128839 | Q38: =I38-P38 -> 0
H40: =SUM(H6:H38) -> 5900 | O40: =SUM(O6:O38) -> 5900

Sheet Index
A2: CB2025-2026.xlsx | B2: Index
A4: S No. | B4: Account | C4: Page No.
A6: 1 | B6: Bank Accounts | C6: 1
A7: 2 | B7: Cash-in-hand | C7: 2
A8: 3 | B8: Current Assets | C8: 3
A9: 4 | B9: ICICI Bank Savings A/c | C9: 4
A10: 5 | B10: Medical Consultation - Freelance | C10: 5
A11: 6 | B11: Miscellaneous | C11: 6
A12: 7 | B12: Movable Assets | C12: 7
A13: 8 | B13: Patients | C13: 8
A14: 9 | B14: Salary | C14: 9
A15: 10 | B15: TDStoIT | C15: 10
A16: 11 | B16: Vehicle Expenditure | C16: 11
A17: 12 | B17: Income Expenditure Account | C17: 12
... A19: 14 | B19: Balance Sheet | C19: 14

Sheet BkAc
A2: CB2025-2026.xlsx | C2: Bank Accounts | E2: LEDGER | G2: Asst. Yr. | H2: 2024-2025
A4: Date | B4: A/c | C4: Description | D4: LD F No. | E4: Debit | F4: Credit | G4: Dr or Cr | H4: Balance
A6: 45382 | B6: ICICI | C6: ICICI Bank Savings A/c | D6: 4 | E6: =ICICI!F41 -> 71950.91 | H6: =BkAc!H5-F6+E6 -> 71950.91
A7: 45382 | B7: CurAs | C7: C/F | D7: 3 | F7: =H6 -> 71950.91 | H7: =BkAc!H6+F7-E7 -> 143901.82

Sheet CiH
A2: CB2025-2026.xlsx | C2: Cash-in-hand | E2: LEDGER | G2: Asst. Yr. | H2: 2024-2025
A4: Date | B4: A/c | C4: Description | D4: CB F No. | E4: Debit | F4: Credit | G4: Dr or Cr | H4: Balance
A6: 45382 | B6: By Balance | C6: B/F | E6: =Mar!N38 -> 121839 | H6: =CiH!H5-F6+E6 -> 121839
A7: 45382 | B7: CurAs | C7: C/F | D7: 3 | F7: =CiH!H6 -> 121839 | H7: =CiH!H6-F7+E7 -> 0

Sheet CurAs
A2: CB2025-2026.xlsx | C2: Current Assets | E2: LEDGER | G2: Asst. Yr. | H2: 2024-2025
A4: Date | B4: A/c | C4: Description | D4: LD F No. | E4: Debit | F4: Credit | G4: Dr or Cr | H4: Balance
A6: 45382 | B6: CiH | C6: Cash-in-hand | D6: 2 | E6: =CiH!F7 -> 121839 | H6: =CurAs!H5-F6+E6 -> 121839
A7: 45382 | B7: BkAc | C7: Bank Accounts | D7: 1 | E7: =BkAc!F7 -> 71950.91 | H7: =CurAs!H6-F7+E7 -> 193789.91
A8: 45382 | B8: MAs | C8: C/F | D8: 7 | F8: =CurAs!H7 -> 193789.91 | H8: =CurAs!H7-F8+E8 -> 0

Sheet ICICI
A2: CB2025-2026.xlsx | C2: ICICI Bank Savings A/c | E2: LEDGER | G2: Asst. Yr. | H2: 2024-2025
A4: Date | B4: A/c | C4: Description | D4: CB F No. | E4: Debit | F4: Credit | G4: Dr or Cr | H4: Balance
A6: 45017 | B6: By Balance | C6: B/F | E6: 160411.91 | H6: =ICICI!H5-F6+E6 -> 160411.91
A7: =Apr!A9 -> 45386 | B7: =Apr!B14 -> 0 | C7: =Apr!C9 -> 0 | D7: 1 | F7: =SUM(Apr!G9:H9) -> 0 | H7: =ICICI!H6-F7+E7 -> 160411.91
A8: =Apr!J27 -> 45404 | B8: =Apr!K27 -> ICICI | C8: =Apr!L27 -> UPI/311273166081/UPI/7409404440.wa.y/Kotak Mahindra /AXISWC3C4DB46691D4D54E08E7 | D8: 1 | E8: =SUM(Apr!N27:O27) -> 300 | H8: =ICICI!H7-F8+E8 -> 160711.91
A9: =May!A8 -> 45415 | B9: =May!B8 -> ICICI | C9: =May!C8 -> NFS/S1ACAG49/CASH WDL/03-05-23 | D9: 2 | F9: =SUM(May!G8:H8) -> 10000 | H9: =ICICI!H8-F9+E9 -> 150711.91
A10: =May!J9 -> 45416 | B10: =May!K9 -> 0 | C10: =May!L9 -> 0 | D10: 2 | E10: =SUM(May!N9:O9) -> 0 | H10: =ICICI!H9-F10+E10 -> 150711.91
A11: =May!A36 -> 45441 | B11: =May!B36 -> ICICI | C11: =May!C36 -> NFS/S1ACAG49/CASH WDL/28-05-23 | D11: 2 | F11: =SUM(May!G36:H36) -> 10000 | H11: =ICICI!H10-F11+E11 -> 140711.91
A12: =Jun!A33 -> 45471 | B12: =Jun!B33 -> ICICI | C12: =Jun!C33 -> NFS/S1ACAG49/CASH WDL/28-06-23 | D12: 3 | F12: =SUM(Jun!G33:H33) -> 10000 | H12: =ICICI!H11-F12+E12 -> 130711.91
A13: =Jul!J24 -> 45492 | B13: =Jul!K24 -> 0 | C13: =Jul!L24 -> 0 | D13: 4 | E13: =SUM(Jul!N24:O24) -> 0 | H13: =ICICI!H12-F13+E13 -> 130711.91
A14: =Jul!A35 -> 45503 | B14: =Jul!B35 -> ICICI | C14: =Jul!C35 -> ATM/S1CNQ071/CASH WDL/29-07-23 | D14: 4 | F14: =SUM(Jul!G35:H35) -> 10000 | H14: =ICICI!H13-F14+E14 -> 120711.91
A15: =Aug!J21 -> 45520 | B15: =Aug!K21 -> 0 | C15: =Aug!L21 -> 0 | D15: 5 | E15: =SUM(Aug!N21:O21) -> 0 | H15: =ICICI!H14-F15+E15 -> 120711.91
A16: =Aug!A34 -> 45533 | B16: =Aug!B34 -> ICICI | C16: =Aug!C34 -> NFS/ID131801/CASH WDL/28-08-23 | D16: 5 | F16: =SUM(Aug!G34:H34) -> 10000 | H16: =ICICI!H15-F16+E16 -> 110711.91
A17: =Sep!A22 -> 45552 | B17: =Sep!B22 -> ICICI | C17: =Sep!C22 -> NFS/S1ACAG49/CASH WDL/17-09-23 | D17: 6 | F17: =SUM(Sep!G22:H22) -> 10000 | H17: =ICICI!H16-F17+E17 -> 100711.91
A18: =Sep!J28 -> 45558 | B18: =Sep!K28 -> 0 | C18: =Sep!L28 -> 0 | D18: 6 | E18: =SUM(Sep!N28:O28) -> 0 | H18: =ICICI!H17-F18+E18 -> 100711.91
A19: =Oct!A27 -> 45587 | B19: =Oct!B27 -> ICICI | C19: =Oct!C27 -> NFS/CASH WDL/329515011779/S1ACAG49/AGRA /22-10 | D19: 7 | F19: =SUM(Oct!G27:H27) -> 5000 | H19: =ICICI!H18-F19+E19 -> 95711.91
A20: =Oct!J32 -> 45592 | B20: =Oct!K32 -> 0 | C20: =Oct!L32 -> 0 | D20: 7 | E20: =SUM(Oct!N32:O32) -> 0 | H20: =ICICI!H19-F20+E20 -> 95711.91
A21: =Nov!J7 -> 45598 | B21: =Nov!K7 -> 0 | C21: =Nov!L7 -> 0 | D21: 8 | E21: =SUM(Nov!N7:O7) -> 0 | H21: =ICICI!H20-F21+E21 -> 95711.91
A22: =Nov!J23 -> 45614 | B22: =Nov!K23 -> ICICI | C22: =Nov!L23 -> 0 | D22: 8 | E22: =SUM(Nov!N23:O23) -> 0 | H22: =ICICI!H21-F22+E22 -> 95711.91
A23: =Nov!J30 -> 45621 | B23: =Nov!K30 -> ICICI | C23: =Nov!L30 -> TRF/SHRI MARUTINANDAN/005255/ICI/13.10.2024 | D23: 8 | E23: =SUM(Nov!N30:O30) -> 6840 | H23: =ICICI!H22-F23+E23 -> 102551.91
A24: =Nov!A34 -> 45622 | B24: =Nov!B34 -> Patients | C24: =Nov!C34 -> CLG/SHRI MARUTI NANDAN HEAL/278323/CAB/06.11.2024 | D24: 8 | F24: =SUM(Nov!G34:H34) -> 4851 | H24: =ICICI!H23-F24+E24 -> 97700.91
A25: =Nov!J38 -> 45626 | B25: =Nov!K38 -> 0 | C25: =Nov!L38 -> 0 | D25: 8 | E25: =SUM(Nov!N38:O38) -> 0 | H25: =ICICI!H24-F25+E25 -> 97700.91
A26: =Dec!J31 -> 45652 | B26: =Dec!K31 -> ICICI | C26: =Dec!L31 -> UPI/aradhanajain.77/fee/UNION BANK OF I/110005115377/UOB8b5a3fb3b56040ac9f1cb2856b871638 | D26: 9 | E26: =SUM(Dec!N31:O31) -> 300 | H26: =ICICI!H25-F26+E26 -> 98000.91
A27: =Dec!A35 -> 45656 | B27: =Dec!B35 -> ICICI | C27: =Dec!C35 -> NFS/CASH WDL/336315013194/S1ACAG49/AGRA /29-12 | D27: 9 | F27: =SUM(Dec!G35:H35) -> 10000 | H27: =ICICI!H26-F27+E27 -> 88000.91
A28: =Jan!J29 -> 45681 | B28: =Jan!K29 -> ICICI | C28: =Jan!L29 -> TRF/SHRI MURTINANDAN HWEALT/004311/ICI/05.01.2024 | D28: 10 | E28: =SUM(Jan!N29:O29) -> 8640 | H28: =ICICI!H27-F28+E28 -> 96640.91
A29: =Jan!A31 -> 45683 | B29: =Jan!B31 -> ICICI | C29: =Jan!C31 -> NFS/CASH WDL/402522024752/S1ACAG49/AGRA /25-01 | D29: 10 | F29: =SUM(Jan!G31:H31) -> 10000 | H29: =ICICI!H28-F29+E29 -> 86640.91
A30: =Feb!J12 -> 45695 | B30: =Feb!K18 -> ICICI | C30: =Feb!L12 -> 0 | D30: 10 | E30: =SUM(Feb!N12:O12) -> 0 | H30: =ICICI!H29-F30+E30 -> 86640.91
A31: =Feb!J14 -> 45697 | B31: =Feb!K14 -> 0 | C31: =Feb!L14 -> 0 | D31: 11 | E31: =SUM(Feb!N14:O14) -> 0 | H31: =ICICI!H30-F31+E31 -> 86640.91
A32: =Feb!A20 -> 45703 | B32: =Feb!B20 -> ICICI | C32: =Feb!C20 -> ATM/S1CNQ071/CASH WDL/13-02-24 | D32: 11 | F32: =SUM(Feb!G20:H20) -> 10000 | H32: =ICICI!H31-F32+E32 -> 76640.91
A33: =Feb!J23 -> 45706 | B33: =Feb!K23 -> 0 | C33: =Feb!L23 -> 0 | D33: 11 | E33: =SUM(Feb!N23:O23) -> 0 | H33: =ICICI!H32-F33+E33 -> 76640.91
A34: =Feb!J25 -> 45708 | B34: =Feb!K25 -> 0 | C34: =Feb!L25 -> 0 | D34: 11 | E34: =SUM(Feb!N25:O25) -> 0 | H34: =ICICI!H33-F34+E34 -> 76640.91
A35: =Feb!J29 -> 45712 | B35: =Feb!K29 -> 0 | C35: =Feb!L29 -> 0 | D35: 11 | E35: =SUM(Feb!N29:O29) -> 0 | H35: =ICICI!H34-F35+E35 -> 76640.91
A36: =Feb!J31 -> 45714 | B36: =Feb!K31 -> 0 | C36: =Feb!L31 -> 0 | D36: 11 | E36: =SUM(Feb!N31:O31) -> 0 | H36: =ICICI!H35-F36+E36 -> 76640.91
A37: =Feb!J35 -> 45716 | B37: =Feb!K35 -> 0 | C37: =Feb!L35 -> 0 | D37: 11 | E37: =SUM(Feb!N35:O35) -> 0 | H37: =ICICI!H36-F37+E37 -> 76640.91
A38: =Mar!J9 -> 45720 | B38: =Mar!K9 -> ICICI | C38: =Mar!L9 -> TRF/SHRI MARUTINANDAN/004572/ICI/25.02.2024 | D38: 12 | E38: =SUM(Mar!N9:O9) -> 2430 | H38: =ICICI!H37-F38+E38 -> 79070.91
A39: =Mar!J21 -> 45732 | B39: =Mar!K21 -> ICICI | C39: =Mar!L21 -> TRFR FROM:SHRI MARUTINANDAN HEALTHCARE PRIVATE LIM | D39: 12 | E39: =SUM(Mar!N21:O21) -> 2880 | H39: =ICICI!H38-F39+E39 -> 81950.91
A40: =Mar!A22 -> 45733 | B40: =Mar!B22 -> ICICI | C40: =Mar!C22 -> NFS/CASH WDL/407521989689/UN224601/AGRA /15-03 | D40: 12 | F40: =SUM(Mar!G22:H22) -> 10000 | H40: =ICICI!H39-F40+E40 -> 71950.91
A41: 45382 | B41: BkAc | C41: C/F | D41: 1 | F41: =H40 -> 71950.91 | H41: =ICICI!H40-F41+E41 -> 0

Sheet Inst
A2: CB2025-2026.xlsx | C2: Instruments | E2: LEDGER | G2: Asst. Yr. | H2: 2024-2025
A4: Date | B4: A/c | C4: Description | D4: CB F No. | E4: Debit | F4: Credit | G4: Dr or Cr | H4: Balance
A6: 44652 | B6: By Balance | C6: B/F | E6: 1359.43 | H6: =Inst!H5-F6+E6 -> 1359.43
A7: 44653 | B7: Instruments | C7: 0 | D7: 1 | E7: 0 | H7: =Inst!H6-F7+E7 -> 1359.43
A8: 45016 | B8: Dep | C8: Depreciation @ 7.5% | F8: =(Inst!H7-Inst!H7)*0.075 -> 0 | H8: =Inst!H7-F8+E8 -> 1359.43
A9: 45016 | B9: Dep | C9: Depreciation @ 15% | F9: =H8*0.15 -> 203.9145 | H9: =Inst!H8-F9+E9 -> 1155.5155
A10: 45016 | B10: MAs | C10: C/F | D10: 7 | F10: =H9 -> 1155.5155 | H10: =Inst!H9-F10+E10 -> 0

Sheet MedCon
A2: CB2025-2026.xlsx | C2: Medical Consultation - Freelance | E2: LEDGER | G2: Asst. Yr. | H2: 2024-2025
A4: Date | B4: A/c | C4: Description | D4: CB F No. | E4: Debit | F4: Credit | G4: Dr or Cr | H4: Balance
A6: =Oct!A32 -> 45592 | B6: =Oct!B32 -> 0 | C6: =Oct!C32 -> 0 | D6: 7 | F6: =SUM(Oct!G32:H32) -> 0 | H6: =MedCon!H5+F6-E6 -> 0
A7: =Nov!A23 -> 45614 | B7: =Nov!B23 -> 0 | C7: =Nov!C23 -> 0 | D7: 8 | F7: =SUM(Nov!G23:H23) -> 0 | H7: =MedCon!H6+F7-E7 -> 0
A8: =Feb!A14 -> 45697 | B8: =Feb!B14 -> 0 | C8: =Feb!C14 -> 0 | D8: 11 | F8: =SUM(Feb!G14:H14) -> 0 | H8: =MedCon!H7+F8-E8 -> 0
A9: =Feb!A35 -> 45716 | B9: =Feb!B35 -> 0 | C9: =Feb!C35 -> 0 | D9: 11 | F9: =SUM(Feb!G35:H35) -> 0 | H9: =MedCon!H8+F9-E9 -> 0
A10: 45382 | B10: Inc.Exp.A/c | C10: C/F | D10: 12 | E10: =H9 -> 0 | H10: =MedCon!H9+F10-E10 -> 0

Sheet misc
A2: CB2025-2026.xlsx | C2: Miscellaneous | E2: LEDGER | G2: Asst. Yr. | H2: 2024-2025
A4: Date | B4: A/c | C4: Description | D4: CB F No. | E4: Debit | F4: Credit | G4: Dr or Cr | H4: Balance
A6: =Apr!J9 -> 45386 | B6: =Apr!K9 -> Misc. | C6: =Apr!L9 -> Stationery | D6: 1 | E6: =SUM(Apr!N9:O9) -> 280 | H6: =misc!H5-F6+E6 -> 280
A7: 45382 | B7: Inc.Exp.A/c | C7: C/F | D7: 12 | F7: =misc!H6 -> 280 | H7: =misc!H6-F7+E7 -> 0

Sheet MAs
A2: CB2025-2026.xlsx | C2: Movable Assets | E2: LEDGER | G2: Asst. Yr. | H2: 2024-2025
A4: Date | B4: A/c | C4: Description | D4: LD F No. | E4: Debit | F4: Credit | G4: Dr or Cr | H4: Balance
A6: 45382 | B6: CurAs | C6: Current Assets | D6: 3 | E6: =CurAs!F8 -> 193789.91 | H6: =MAs!H5-F6+E6 -> 193789.91
A7: 45382 | B7: Bal | C7: C/F | D7: 14 | F7: =MAs!H6 -> 193789.91 | H7: =MAs!H6-F7+E7 -> 0

Sheet Pt
A2: CB2025-2026.xlsx | C2: Patients | E2: LEDGER | G2: Asst. Yr. | H2: 2024-2025
A4: Date | B4: A/c | C4: Description | D4: CB F No. | E4: Debit | F4: Credit | G4: Dr or Cr | H4: Balance
A6: =Apr!A27 -> 45404 | B6: =Apr!B15 -> Patients | C6: =Apr!C27 -> 0 | D6: 1 | F6: =SUM(Apr!G27:H27) -> 300 | H6: =Pt!H5+F6-E6 -> 300
A7: =May!A9 -> 45416 | B7: =May!B9 -> 0 | C7: =May!C9 -> 0 | D7: 2 | F7: =SUM(May!G9:H9) -> 0 | H7: =Pt!H6+F7-E7 -> 300
A8: =Jul!A24 -> 45492 | B8: =Jul!B24 -> 0 | C8: =Jul!C24 -> 0 | D8: 4 | F8: =SUM(Jul!G24:H24) -> 0 | H8: =Pt!H7+F8-E8 -> 300
A9: =Aug!A21 -> 45520 | B9: =Aug!B21 -> 0 | C9: =Aug!C21 -> 0 | D9: 5 | F9: =SUM(Aug!G21:H21) -> 0 | H9: =Pt!H8+F9-E9 -> 300
A10: =Sep!A28 -> 45558 | B10: =Sep!B28 -> 0 | C10: =Sep!C28 -> 0 | D10: 6 | F10: =SUM(Sep!G28:H28) -> 0 | H10: =Pt!H9+F10-E10 -> 300
A11: =Nov!A7 -> 45598 | B11: =Nov!B7 -> 0 | C11: =Nov!C7 -> 0 | D11: 8 | F11: =SUM(Nov!G7:H7) -> 0 | H11: =Pt!H10+F11-E11 -> 300
A12: =Nov!A30 -> 45621 | B12: =Nov!B30 -> Patients | C12: =Nov!C30 -> TRF/SHRI MARUTINANDAN/005255/ICI/13.10.2024 | D12: 8 | F12: =SUM(Nov!G30:H30) -> 7524 | H12: =Pt!H11+F12-E12 -> 7824
A13: =Nov!A38 -> 45626 | B13: =Nov!B38 -> 0 | C13: =Nov!C38 -> 0 | D13: 8 | F13: =SUM(Nov!G38:H38) -> 0 | H13: =Pt!H12+F13-E13 -> 7824
A14: =Dec!A31 -> 45652 | B14: =Dec!B31 -> Patients | C14: =Dec!C31 -> UPI/aradhanajain.77/fee/UNION BANK OF I/110005115377/UOB8b5a3fb3b56040ac9f1cb2856b871638 | D14: 9 | F14: =SUM(Dec!G31:H31) -> 300 | H14: =Pt!H13+F14-E14 -> 8124
A15: =Jan!A29 -> 45681 | B15: =Jan!B29 -> Patients | C15: =Jan!C29 -> TRF/SHRI MURTINANDAN HWEALT/004311/ICI/05.01.2024 | D15: 10 | F15: =SUM(Jan!G29:H29) -> 9600 | H15: =Pt!H14+F15-E15 -> 17724
A16: =Feb!A12 -> 45695 | B16: =Feb!B12 -> 0 | C16: =Feb!C12 -> 0 | D16: 11 | F16: =SUM(Feb!G12:H12) -> 0 | H16: =Pt!H15+F16-E16 -> 17724
A17: =Feb!A23 -> 45706 | B17: =Feb!B23 -> 0 | C17: =Feb!C23 -> 0 | D17: 11 | F17: =SUM(Feb!G23:H23) -> 0 | H17: =Pt!H16+F17-E17 -> 17724
A18: =Feb!A25 -> 45708 | B18: =Feb!B25 -> 0 | C18: =Feb!C25 -> 0 | D18: 11 | F18: =SUM(Feb!G25:H25) -> 0 | H18: =Pt!H17+F18-E18 -> 17724
A19: =Feb!A29 -> 45712 | B19: =Feb!B29 -> 0 | C19: =Feb!C29 -> 0 | D19: 11 | F19: =SUM(Feb!G29:H29) -> 0 | H19: =Pt!H18+F19-E19 -> 17724
A20: =Feb!A31 -> 45714 | B20: =Feb!B31 -> 0 | C20: =Feb!C31 -> 0 | D20: 11 | F20: =SUM(Feb!G31:H31) -> 0 | H20: =Pt!H19+F20-E20 -> 17724
A21: =Mar!A9 -> 45720 | B21: =Mar!B9 -> Patients | C21: =Mar!C9 -> TRF/SHRI MARUTINANDAN/004572/ICI/25.02.2024 | D21: 12 | F21: =SUM(Mar!G9:H9) -> 2700 | H21: =Pt!H20+F21-E21 -> 20424
A22: =Mar!A21 -> 45732 | B22: =Mar!B21 -> Patients | C22: =Mar!C21 -> TRFR FROM:SHRI MARUTINANDAN HEALTHCARE PRIVATE LIM | D22: 12 | F22: =SUM(Mar!G21:H21) -> 3200 | H22: =Pt!H21+F22-E22 -> 23624
A23: 45382 | B23: Inc.Exp.A/c | C23: C/F | D23: 12 | E23: =H22 -> 23624 | H23: =Pt!H22+F23-E23 -> 0

Sheet Salary
A2: CB2025-2026.xlsx | C2: Salary | E2: LEDGER | G2: Asst. Yr. | H2: 2024-2025
A4: Date | B4: A/c | C4: Description | D4: CB F No. | E4: Debit | F4: Credit | G4: Dr or Cr | H4: Balance
A6: =Apr!J8 -> 45385 | B6: =Apr!K8 -> Salary | C6: =Apr!L8 -> Neeraj | D6: 1 | E6: =SUM(Apr!N8:O8) -> 3000 | H6: =Salary!H5-F6+E6 -> 3000
A7: =Apr!J26 -> 45403 | B7: =Apr!K26 -> Salary | C7: =Apr!L26 -> Gaurav | D7: 1 | E7: =SUM(Apr!N26:O26) -> 3000 | H7: =Salary!H6-F7+E7 -> 6000
A8: =May!J12 -> 45419 | B8: =May!K12 -> Salary | C8: =May!L12 -> Neeraj | D8: 2 | E8: =SUM(May!N12:O12) -> 3000 | H8: =Salary!H7-F8+E8 -> 9000
A9: =May!J27 -> 45434 | B9: =May!K27 -> ICICI | C9: =May!L27 -> TRF/MARUTINANDAN HEALTHCARE/004877/ICI/03.05.2024 | D9: 2 | E9: =SUM(May!N27:O27) -> 2160 | H9: =Salary!H8-F9+E9 -> 11160
A10: =Jun!J8 -> 45444 | B10: =Jun!K8 -> TDStoIT | C10: =Jun!L8 -> 0 | D10: 3 | E10: =SUM(Jun!N8:O8) -> 630 | H10: =Salary!H9-F10+E10 -> 11790
A11: =Jun!J27 -> 45465 | B11: =Jun!K27 -> Salary | C11: =Jun!L27 -> Gaurav | D11: 3 | E11: =SUM(Jun!N27:O27) -> 3000 | H11: =Salary!H10-F11+E11 -> 14790
A12: =Jul!J9 -> 45477 | B12: =Jul!K9 -> Salary | C12: =Jul!L9 -> Neeraj | D12: 4 | E12: =SUM(Jul!N9:O9) -> 3000 | H12: =Salary!H11-F12+E12 -> 17790
A13: =Jul!J28 -> 45496 | B13: =Jul!K28 -> Salary | C13: =Jul!L28 -> Gaurav | D13: 4 | E13: =SUM(Jul!N28:O28) -> 3000 | H13: =Salary!H12-F13+E13 -> 20790
A14: =Aug!J7 -> 45506 | B14: =Aug!K7 -> Salary | C14: =Aug!L7 -> Neeraj | D14: 5 | E14: =SUM(Aug!N7:O7) -> 3000 | H14: =Salary!H13-F14+E14 -> 23790
A15: =Aug!J29 -> 45527 | B15: =Aug!K29 -> ICICI | C15: =Aug!L29 -> CLG/SHRI MARUTI NANDAN/278144/CAB/08.08.2024 | D15: 5 | E15: =SUM(Aug!N29:O29) -> 11160 | H15: =Salary!H14-F15+E15 -> 34950
A16: =Sep!J7 -> 45537 | B16: =Sep!K7 -> Salary | C16: =Sep!L7 -> Neeraj | D16: 6 | E16: =SUM(Sep!N7:O7) -> 3000 | H16: =Salary!H15-F16+E16 -> 37950
A17: =Sep!J25 -> 45555 | B17: =Sep!K25 -> Salary | C17: =Sep!L25 -> Gaurav | D17: 6 | E17: =SUM(Sep!N25:O25) -> 3000 | H17: =Salary!H16-F17+E17 -> 40950
A18: =Oct!J7 -> 45567 | B18: =Oct!K7 -> Veh. Exp. | C18: =Oct!L7 -> Petrol | D18: 7 | E18: =SUM(Oct!N7:O7) -> 1000 | H18: =Salary!H17-F18+E18 -> 41950
A19: =Oct!J25 -> 45585 | B19: =Oct!K25 -> Salary | C19: =Oct!L25 -> Gaurav | D19: 7 | E19: =SUM(Oct!N25:O25) -> 3000 | H19: =Salary!H18-F19+E19 -> 44950
A20: =Nov!J9 -> 45600 | B20: =Nov!K9 -> Salary | C20: =Nov!L9 -> Neeraj | D20: 8 | E20: =SUM(Nov!N9:O9) -> 3000 | H20: =Salary!H19-F20+E20 -> 47950
A21: =Nov!J22 -> 45613 | B21: =Nov!K22 -> Salary | C21: =Nov!L22 -> Gaurav | D21: 8 | E21: =SUM(Nov!N22:O22) -> 3000 | H21: =Salary!H20-F21+E21 -> 50950
A22: =Dec!J7 -> 45628 | B22: =Dec!K7 -> Salary | C22: =Dec!L7 -> Neeraj | D22: 9 | E22: =SUM(Dec!N7:O7) -> 3000 | H22: =Salary!H21-F22+E22 -> 53950
A23: =Dec!J26 -> 45647 | B23: =Dec!K26 -> Salary | C23: =Dec!L26 -> Gaurav | D23: 9 | E23: =SUM(Dec!N26:O26) -> 3000 | H23: =Salary!H22-F23+E23 -> 56950
A24: =Jan!J7 -> 45659 | B24: =Jan!K7 -> Salary | C24: =Jan!L7 -> Neeraj | D24: 10 | E24: =SUM(Jan!N7:O7) -> 3000 | H24: =Salary!H23-F24+E24 -> 59950
A25: =Jan!J25 -> 45677 | B25: =Jan!K25 -> Salary | C25: =Jan!L25 -> Gaurav | D25: 10 | E25: =SUM(Jan!N25:O25) -> 3000 | H25: =Salary!H24-F25+E25 -> 62950
A26: =Feb!J7 -> 45690 | B26: =Feb!K7 -> Salary | C26: =Feb!L7 -> Neeraj | D26: 11 | E26: =SUM(Feb!N7:O7) -> 3000 | H26: =Salary!H25-F26+E26 -> 65950
A27: =Feb!J28 -> 45711 | B27: =Feb!K28 -> Salary | C27: =Feb!L28 -> Gaurav | D27: 11 | E27: =SUM(Feb!N28:O28) -> 3000 | H27: =Salary!H26-F27+E27 -> 68950
A28: =Mar!J7 -> 45718 | B28: =Mar!K7 -> Salary | C28: =Mar!L7 -> Neeraj | D28: 12 | E28: =SUM(Mar!N7:O7) -> 3000 | H28: =Salary!H27-F28+E28 -> 71950
A29: =Mar!J25 -> 45736 | B29: =Mar!K25 -> Salary | C29: =Mar!L25 -> Gaurav | D29: 12 | E29: =SUM(Mar!N25:O25) -> 3000 | H29: =Salary!H28-F29+E29 -> 74950
A30: 45382 | B30: Inc.Exp.A/c | C30: C/F | D30: 12 | F30: =Salary!H29 -> 74950 | H30: =Salary!H29-F30+E30 -> 0

Sheet TDStoIT
A2: CB2025-2026.xlsx | C2: TDStoIT | E2: LEDGER | G2: Asst. Yr. | H2: 2024-2025
A4: Date | B4: A/c | C4: Description | D4: CB F No. | E4: Debit | F4: Credit | G4: Dr or Cr | H4: Balance
A6: =Jul!J25 -> 45493 | B6: =Jul!K25 -> 0 | C6: =Jul!L25 -> 0 | D6: 4 | E6: =SUM(Jul!N25:O25) -> 0 | H6: =TDStoIT!H5-F6+E6 -> 0
A7: =Aug!J22 -> 45521 | B7: =Aug!K22 -> 0 | C7: =Aug!L22 -> 0 | D7: 5 | E7: =SUM(Aug!N22:O22) -> 0 | H7: =TDStoIT!H6-F7+E7 -> 0
A8: =Oct!J33 -> 45593 | B8: =Oct!K33 -> 0 | C8: =Oct!L33 -> 0 | D8: 7 | E8: =SUM(Oct!N33:O33) -> 0 | H8: =TDStoIT!H7-F8+E8 -> 0
A9: =Nov!J8 -> 45599 | B9: =Nov!K8 -> 0 | C9: =Nov!L8 -> 0 | D9: 8 | E9: =SUM(Nov!N8:O8) -> 0 | H9: =TDStoIT!H8-F9+E9 -> 0
A10: =Nov!J24 -> 45615 | B10: =Nov!K24 -> TDStoIT | C10: =Nov!L24 -> 0 | D10: 8 | E10: =SUM(Nov!N24:O24) -> 0 | H10: =TDStoIT!H9-F10+E10 -> 0
A11: =Nov!J31 -> 45621 | B11: =Nov!K31 -> TDStoIT | C11: =Nov!L31 -> 0 | D11: 8 | E11: =SUM(Nov!N31:O31) -> 684 | H11: =TDStoIT!H10-F11+E11 -> 684
A12: =Nov!J39 -> 45626 | B12: =Nov!K39 -> 0 | C12: =Nov!L39 -> 0 | D12: 8 | E12: =SUM(Nov!N39:O39) -> 0 | H12: =TDStoIT!H11-F12+E12 -> 684
A13: =Dec!J32 -> 45653 | B13: =Dec!K32 -> 0 | C13: =Dec!L32 -> 0 | D13: 9 | E13: =SUM(Dec!N32:O32) -> 0 | H13: =TDStoIT!H12-F13+E13 -> 684
A14: =Jan!J30 -> 45682 | B14: =Jan!K30 -> TDStoIT | C14: =Jan!L30 | D14: 10 | E14: =SUM(Jan!N30:O30) -> 960 | H14: =TDStoIT!H13-F14+E14 -> 1644
A15: =Feb!J13 -> 45696 | B15: =Feb!K19 -> TDStoIT | D15: 11 | E15: =SUM(Feb!N13:O13) -> 0 | H15: =TDStoIT!H14-F15+E15 -> 1644
A16: =Feb!J15 -> 45698 | B16: =Feb!K15 -> 0 | D16: 11 | E16: =SUM(Feb!N15:O15) -> 0 | H16: =TDStoIT!H15-F16+E16 -> 1644
A17: =Feb!J24 -> 45707 | B17: =Feb!K24 -> 0 | C17: =Feb!L16 | D17: 11 | E17: =SUM(Feb!N24:O24) -> 0 | H17: =TDStoIT!H16-F17+E17 -> 1644
A18: =Feb!J26 -> 45709 | B18: =Feb!K26 -> 0 | D18: 11 | E18: =SUM(Feb!N26:O26) -> 0 | H18: =TDStoIT!H17-F18+E18 -> 1644
A19: =Feb!J30 -> 45713 | B19: =Feb!K30 -> 0 | D19: 11 | E19: =SUM(Feb!N30:O30) -> 0 | H19: =TDStoIT!H18-F19+E19 -> 1644
A20: =Feb!J32 -> 45715 | B20: =Feb!K32 -> 0 | D20: 11 | E20: =SUM(Feb!N32:O32) -> 0 | H20: =TDStoIT!H19-F20+E20 -> 1644
A21: =Feb!J36 -> 45716 | B21: =Feb!K36 -> 0 | C21: =Feb!L36 -> 0 | D21: 11 | E21: =SUM(Feb!N36:O36) -> 0 | H21: =TDStoIT!H20-F21+E21 -> 1644
A22: =Mar!J10 -> 45721 | B22: =Mar!K10 -> TDStoIT | C22: =Mar!L10 | D22: 12 | E22: =SUM(Mar!N10:O10) -> 270 | H22: =TDStoIT!H21-F22+E22 -> 1914
A23: =Mar!J22 -> 45733 | B23: =Mar!K22 -> TDStoIT | C23: =Mar!L22 | D23: 12 | E23: =SUM(Mar!N22:O22) -> 320 | H23: =TDStoIT!H22-F23+E23 -> 2234
A24: 45382 | B24: CapAc | C24: C/F | D24: 13 | F24: =H23 -> 2234 | H24: =TDStoIT!H23-F24+E24 -> 0

Sheet vehexp
A2: CB2025-2026.xlsx | C2: Vehicle Expenditure | E2: LEDGER | G2: Asst. Yr. | H2: 2024-2025
A4: Date | B4: A/c | C4: Description | D4: CB F No. | E4: Debit | F4: Credit | G4: Dr or Cr | H4: Balance
A6: =Apr!J20 -> 45397 | B6: =Apr!K20 -> Veh. Exp. | C6: =Apr!L20 -> Petrol | D6: 1 | E6: =SUM(Apr!N20:O20) -> 500 | H6: =vehexp!H5-F6+E6 -> 500
A7: =May!J19 -> 45426 | B7: =May!K19 -> Veh. Exp. | C7: =May!L19 -> Petrol | D7: 2 | E7: =SUM(May!N19:O19) -> 500 | H7: =vehexp!H6-F7+E7 -> 1000
A8: =May!J37 -> 45442 | B8: =May!K37 -> Veh. Exp. | C8: =May!L37 -> Petrol | D8: 2 | E8: =SUM(May!N37:O37) -> 2000 | H8: =vehexp!H7-F8+E8 -> 3000
A9: =Jun!J22 -> 45460 | B9: =Jun!K22 -> Veh. Exp. | C9: =Jun!L22 -> Petrol | D9: 3 | E9: =SUM(Jun!N22:O22) -> 500 | H9: =vehexp!H8-F9+E9 -> 3500
A10: =Jul!J16 -> 45484 | B10: =Jul!K16 -> Veh. Exp. | C10: =Jul!L16 -> Petrol | D10: 4 | E10: =SUM(Jul!N16:O16) -> 500 | H10: =vehexp!H9-F10+E10 -> 4000
A11: =Jul!J34 -> 45502 | B11: =Jul!K34 -> Veh. Exp. | C11: =Jul!L34 -> Petrol | D11: 4 | E11: =SUM(Jul!N34:O34) -> 500 | H11: =vehexp!H10-F11+E11 -> 4500
A12: =Aug!J32 -> 45531 | B12: =Aug!K32 -> Veh. Exp. | C12: =Aug!L32 -> Petrol | D12: 5 | E12: =SUM(Aug!N32:O32) -> 500 | H12: =vehexp!H11-F12+E12 -> 5000
A13: =Sep!J14 -> 45544 | B13: =Sep!K14 -> 0 | C13: =Sep!L14 -> 0 | D13: 6 | E13: =SUM(Sep!N14:O14) -> 0 | H13: =vehexp!H12-F13+E13 -> 5000
A14: =Sep!J33 -> 45563 | B14: =Sep!K33 -> Veh. Exp. | C14: =Sep!L33 -> Petrol | D14: 6 | E14: =SUM(Sep!N33:O33) -> 500 | H14: =vehexp!H13-F14+E14 -> 5500
A15: =Oct!J13 -> 45568 | B15: =Oct!K20 -> Veh. Exp. | C15: =Oct!L20 -> Petrol | D15: 7 | E15: =SUM(Oct!N13:O13) -> 414 | H15: =vehexp!H14-F15+E15 -> 5914
A16: =Oct!J30 -> 45590 | B16: =Oct!K30 -> Veh. Exp. | C16: =Oct!L30 -> Petrol | D16: 7 | E16: =SUM(Oct!N30:O30) -> 500 | H16: =vehexp!H15-F16+E16 -> 6414
A17: =Nov!J10 -> 45601 | B17: =Nov!K10 -> Veh. Exp. | C17: =Nov!L10 -> Petrol | D17: 8 | E17: =SUM(Nov!N10:O10) -> 500 | H17: =vehexp!H16-F17+E17 -> 6914
A18: =Nov!J33 -> 45622 | B18: =Nov!K33 -> TDStoIT | C18: =Nov!L33 -> 0 | D18: 8 | E18: =SUM(Nov!N33:O33) -> 414 | H18: =vehexp!H17-F18+E18 -> 7328
A19: =Dec!J33 -> 45654 | B19: =Dec!K33 -> Veh. Exp. | C19: =Dec!L33 -> Petrol | D19: 9 | E19: =SUM(Dec!N33:O33) -> 500 | H19: =vehexp!H18-F19+E19 -> 7828
A20: =Jan!J9 -> 45660 | B20: =Jan!K9 -> TDStoIT | C20: =Jan!L9 -> 0 | D20: 10 | E20: =SUM(Jan!N9:O9) -> 468 | H20: =vehexp!H19-F20+E20 -> 8296
A21: =Jan!J27 -> 45679 | B21: =Jan!K27 -> Veh. Exp. | C21: =Jan!L27 -> Petrol | D21: 10 | E21: =SUM(Jan!N27:O27) -> 500 | H21: =vehexp!H20-F21+E21 -> 8796
A22: =Feb!J10 -> 45693 | B22: =Feb!K10 -> ICICI | C22: =Feb!L10 -> UPI/avneshjain.agra/UPI/UNION BANK OF I/540232791818/ICI0f58808fdff34a76848506c81c218908 | D22: 11 | E22: =SUM(Feb!N10:O10) -> 300 | H22: =vehexp!H21-F22+E22 -> 9096
A23: =Mar!J14 -> 45725 | B23: =Mar!K14 -> Veh. Exp. | C23: =Mar!L14 -> Petrol | D23: 12 | E23: =SUM(Mar!N14:O14) -> 500 | H23: =vehexp!H22-F23+E23 -> 9596
A24: =Mar!J34 -> 45745 | B24: =Mar!K34 -> Veh. Exp. | C24: =Mar!L34 -> Petrol | D24: 12 | E24: =SUM(Mar!N34:O34) -> 500 | H24: =vehexp!H23-F24+E24 -> 10096
A25: 45382 | B25: Inc.Exp.A/c | C25: C/F | D25: 12 | F25: =vehexp!H24 -> 10096 | H25: =vehexp!H24-F25+E25 -> 0

Sheet Dep
A2: CB2025-2026.xlsx | C2: Depreciation Account | E2: LEDGER | G2: Asst. Yr. | H2: 2024-2025
A4: Date | B4: A/c | C4: Description | D4: LD F No. | E4: Debit | F4: Credit | G4: Dr or Cr | H4: Balance
A6: 45016 | B6: Instruments | C6: Instruments @ 7.5 % | D6: 5 | E6: =Inst!F8 -> 0 | H6: =H5+E6-F6 -> 0
A7: 45016 | B7: Instruments | C7: Instruments @ 15 % | D7: 5 | E7: =Inst!F9 -> 203.9145 | H7: =H6+E7-F7 -> 203.9145
A8: 45016 | B8: Inc.Exp.A/c | C8: C/F | D8: 14 | F8: =H7 -> 203.9145 | H8: =H7+E8-F8 -> 0

Sheet InExp
A2: CB2025-2026.xlsx | C2: Income Expenditure Account | E2: LEDGER | G2: Asst. Yr. | H2: 2024-2025
A4: Date | B4: A/c | C4: Description | D4: LD F No. | E4: Debit | F4: Credit | G4: Dr or Cr | H4: Balance
A6: 45382 | B6: Dep | C6: Depreciation Account | D6: 13 | E6: =Dep!F8 -> 203.9145 | H6: =H5+F6-E6 -> -203.9145
A7: 45382 | B7: Salary | C7: Salary | D7: 9 | E7: =Salary!F30 -> 74950 | H7: =H6+F7-E7 -> -75153.914
A8: 45382 | B8: Misc. | C8: Miscellaneous | D8: 6 | E8: =misc!F7 -> 280 | H8: =H7+F8-E8 -> -75433.914
A9: 45382 | B9: Veh. Exp. | C9: Vehicle Expenditure | D9: 11 | E9: =vehexp!F25 -> 10096 | H9: =H8+F9-E9 -> -85529.914
A10: 45382 | B10: Patients | C10: Patients | D10: 8 | F10: =Pt!E23 -> 23624 | H10: =H9+F10-E10 -> -61905.914
A11: 45382 | B11: Med.Cons. | C11: Medical Consultation - Freelance | D11: 5 | F11: =MedCon!E10 -> 0 | H11: =H10+F11-E11 -> -61905.914
A12: 45382 | B12: CapAc | C12: C/F | D12: 15 | E12: =InExp!H11 -> -61905.914 | H12: =InExp!H11+F12-E12 -> 0
D14: Expenditure => | E14: =SUM(E6:E11) -> 85529.914 | F14: =SUM(F6:F11) -> 23624 | G14: <= Reciepts
D16: Profit% | E16: =E12/F14 -> -2.6204671

Sheet CapAc
A2: CB2025-2026.xlsx | C2: Capital Account | E2: LEDGER | G2: Asst. Yr. | H2: 2024-2025
A4: Date | B4: A/c | C4: Description | D4: LD F No. | E4: Debit | F4: Credit | G4: Dr or Cr | H4: Balance
A6: 45017 | B6: By Balance | C6: B/F | F6: 194170.35 | H6: =CapAc!H5+F6-E6 -> 194170.35
A7: 45382 | B7: Inc.Exp.A/c | C7: Income from Proffession | D7: 12 | F7: =InExp!E12 -> -61905.914 | H7: =CapAc!H6+F7-E7 -> 132264.43
A8: 45382 | B8: TDStoIT | C8: TDStoIT | D8: 10 | E8: =TDStoIT!F24 -> 2234 | H8: =CapAc!H7+F8-E8 -> 130030.43
A9: 45382 | B9: Bal | C9: C/F | D9: 14 | E9: =CapAc!H8 -> 130030.43 | H9: =CapAc!H8+F9-E9 -> 0

Sheet Bal
A2: CB2025-2026.xlsx | C2: Balance Sheet | E2: LEDGER | G2: Asst. Yr. | H2: 2024-2025
A4: Date | B4: A/c | C4: Description | D4: LD F No. | E4: Debit | F4: Credit | G4: Dr or Cr | H4: Balance
A6: 45382 | B6: MAs | C6: Movable Assets | D6: 7 | H6: =Bal!H5-F6+E6 -> 0
C7: bank acs | E7: =BkAc!F7 -> 71950.91 | H7: =Bal!H6-F7+E7 -> 71950.91
C8: cih | E8: =CiH!F7 -> 121839 | H8: =Bal!H7-F8+E8 -> 193789.91
C9: Instruments | E9: =Inst!F10 -> 1155.5155 | H9: =Bal!H8-F9+E9 -> 194945.43
A10: 45382 | B10: CapAc | C10: Capital Account | D10: 13 | F10: =CapAc!E9 -> 130030.43 | H10: =Bal!H9-F10+E10 -> 64914.994
E11: =SUM(E6:E10) -> 194945.43 | F11: =SUM(F6:F10) -> 130030.43
A15: Dr. Anurag Gupta | B15: PAN No: | C15: AFIPG7802B | E15: ASST YEAR 2023-2024
B16: BALANCE SHEET – PROFESSION
C17: Balance Sheet
B18: Liabilities | F18: Assets
A20: 45016 | B20: CapAc | C20: Capital Account | D20: =CapAc!E9 -> 130030.43 | F20: ImAs | G20: Immovable Assets | I20: 0
A21: 45016 | B21: CurLb | C21: Current Liabilities | D21: 0 | F21: MAs | G21: Movable Assets
A22: 45016 | B22: SCr | C22: Sundry Creditors | D22: 0 | F22: CurAs | G22: Current Assets
A23: 45016 | B23: L&A | C23: Loans And Advances | D23: 0 | F23: Dp | H23: Deposits (Assets) | I23: 0
A24: 45016 | F24: BkAc | H24: Bank Accounts | I24: =BkAc!F7 -> 71950.91
A25: 45016 | F25: SiH | H25: Stock-in-hand | I25: 0
A26: 45016 | F26: CiH | H26: Cash-in-hand | I26: =CiH!F7 -> 121839
A27: 45016 | F27: Inv | G27: Investments
A28: 45016 | F28: Shares | H28: Shares | I28: 0
A29: 45016 | F29: MFund | H29: Mutual Fund | I29: 0
A30: 45016 | F30: Furniture | G30: Furniture | I30: 0
A31: 45016 | F31: Instruments | G31: Instruments | I31: =Inst!F10 -> 1155.5155
A32: 45016 | F32: Sdr | G32: Sundry Debitors | I32: 0
A33: 45016
C35: Total | D35: =SUM(D20:D33) -> 130030.43 | F35: Total | I35: =SUM(I20:I33) -> 194945.43
